<DOMSymbolItem xmlns:xsi="http://www.w3.org/2001/XMLSchema-instance" xmlns="http://ns.adobe.com/xfl/2008/" name="特警僵尸/代码层/蛙型仿生僵尸/人物素材/小腿" itemID="65ab84ee-000003bf" lastModified="1705739506">
  <timeline>
    <DOMTimeline name="小腿">
      <layers>
        <DOMLayer name="图层_3" color="#FF800A" current="true" isSelected="true">
          <frames>
            <DOMFrame index="0" keyMode="9728">
              <elements/>
            </DOMFrame>
          </frames>
        </DOMLayer>
        <DOMLayer name="图层_2" color="#9933CC">
          <frames>
            <DOMFrame index="0" keyMode="9728">
              <elements>
                <DOMShape>
                  <fills>
                    <FillStyle index="1">
                      <SolidColor color="#B0A99F"/>
                    </FillStyle>
                    <FillStyle index="2">
                      <SolidColor color="#E1EAEF"/>
                    </FillStyle>
                    <FillStyle index="3">
                      <SolidColor color="#8AA0AB"/>
                    </FillStyle>
                  </fills>
                  <strokes>
                    <StrokeStyle index="1">
                      <SolidStroke scaleMode="normal">
                        <fill>
                          <SolidColor/>
                        </fill>
                      </SolidStroke>
                    </StrokeStyle>
                  </strokes>
                  <edges>
                    <Edge fillStyle0="3" strokeStyle="1" edges="!-365 1975|-432 1600!-432 1600[-433 1588 -434 1576!-434 1576[-501 1007 -921 3!-921 3[-922 0 -923 -2!-923 -2[-954 -83 -994 -169!-994 -169|-1068 -202!-1068 -202[-1180 -202 -1232 -74!-1232 -74[-1275 30 -1273 117!-1273 117[-1245 231 -1220
 335!-1220 335[-1052 1040 -999 1253!-999 1253[-968 1379 -963 1478!-963 1478[-956 1510 -948 1540!-948 1540[-855 1892 -773 2065"/>
                    <Edge fillStyle0="3" fillStyle1="1" strokeStyle="1" edges="
!-773 2065[-762 2079 -758 2095"/>
                    <Edge fillStyle0="3" strokeStyle="1" edges="
!-758 2095[-730 2183 -699 2254!-699 2254[-684 2288 -667 2319!-667 2319[-635 2381 -598 2427!-598 2427[-518 2525 -511 2523"/>
                    <Edge fillStyle0="3" edges="
!-511 2523[-510 2523 -511 2520!-511 2520[-241 2493 -298 2218"/>
                    <Edge fillStyle0="3" strokeStyle="1" edges="
!-298 2218[-301 2217 -299 2216!-299 2216[-299 2215 -298 2215"/>
                    <Edge strokeStyle="1" edges="
!-298 2215[-298 2216 -298 2218"/>
                    <Edge fillStyle0="2" fillStyle1="3" edges="
!-1154 260[-986 -37 -830 1629!-830 1629[-593 2081 -621 2246!-621 2246[-489 2404 -435 2203!-435 2203[-484 2326 -586 1427!-586 1427|-994 24!-994 24[-1098 83 -1154 260"/>
                    <Edge fillStyle0="3" strokeStyle="1" edges="
!-298 2215[-299 2213 -299 2211!-299 2211[-304 2192 -309 2178!-309 2178|-311 2173!-311 2173|-365 1975"/>
                    <Edge fillStyle0="3" fillStyle1="3" strokeStyle="1" edges="
!-365 1975|-354 2039"/>
                    <Edge fillStyle0="1" strokeStyle="1" edges="
!-773 2065[-766 2080 -759 2095"/>
                    <Edge fillStyle0="1" edges="
!-759 2095|-758 2095"/>
                    <Edge cubics="!-999 1253(;-978,1337 -967,1412 -963,1478q-999 1253Q-968 1379q-963 1478);"/>
                    <Edge cubics="!-963 1478(;-959,1500 -954,1520 -948,1540q-963 1478Q-956 1510q-948 1540);"/>
                    <Edge cubics="!-365 1975(;-365,1975 -432,1600 -432,1600q-365 1975 -432 1600);"/>
                    <Edge cubics="!-354 2039(;-354,2039 -365,1975 -365,1975q-354 2039 -365 1975);"/>
                    <Edge cubics="!-309 2178(;-307,2187 -304,2198 -299,2211q-309 2178Q-304 2192q-299 2211);"/>
                    <Edge cubics="!-309 2178(;-309,2178 -311,2173 -311,2173q-309 2178 -311 2173);"/>
                    <Edge cubics="!-311 2173(;-311,2173 -365,1975 -365,1975q-311 2173 -365 1975);"/>
                    <Edge cubics="!-773 2065(;-766,2074 -761,2084 -758,2095q-773 2065Q-762 2079q-758 2095);"/>
                    <Edge cubics="!-773 2065(;-768,2075 -764,2085 -759,2095q-773 2065Q-766 2080q-759 2095);"/>
                    <Edge cubics="!-758 2095(;-758,2095 -759,2095 -759,2095q-758 2095 -759 2095);"/>
                    <Edge cubics="!-948 1540(;-886,1775 -828,1950 -773,2065q-948 1540Q-855 1892q-773 2065);"/>
                    <Edge cubics="!-299 2211(;-299,2212 -299,2214 -298,2215q-299 2211Q-299 2213q-298 2215);"/>
                    <Edge cubics="!-299 2216(;-299,2215 -299,2215 -298,2215q-299 2216Q-299 2215q-298 2215);"/>
                    <Edge cubics="!-298 2215(;-298,2216 -298,2217 -298,2218q-298 2215Q-298 2216q-298 2218);"/>
                    <Edge cubics="!-298 2218(;-299,2217 -301,2217 -299,2216q-298 2218Q-301 2217q-299 2216);"/>
                    <Edge cubics="!-511 2523(;-510,2523 -510,2522 -511,2520q-511 2523Q-510 2523q-511 2520);"/>
                    <Edge cubics="!-298 2218(;-260,2401 -332,2502 -511,2520q-298 2218Q-241 2493q-511 2520);"/>
                    <Edge cubics="!-598 2427(;-545,2492 -516,2524 -511,2523q-598 2427Q-518 2525q-511 2523);"/>
                    <Edge cubics="!-432 1600(;-433,1592 -433,1584 -434,1576q-432 1600Q-433 1588q-434 1576);"/>
                    <Edge cubics="!-434 1576(;-478,1197 -641,672 -921,3q-434 1576Q-501 1007q-921 3);"/>
                    <Edge cubics="!-667 2319(;-646,2360 -623,2396 -598,2427q-667 2319Q-635 2381q-598 2427);"/>
                    <Edge cubics="!-1232 -74(;-1261,-5 -1274,59 -1273,117q-1232 -74Q-1275 30q-1273 117);"/>
                    <Edge cubics="!-923 -2(;-943,-56 -967,-112 -994,-169q-923 -2Q-954 -83q-994 -169);"/>
                    <Edge cubics="!-1273 117(;-1255,193 -1237,266 -1220,335q-1273 117Q-1245 231q-1220 335);"/>
                    <Edge cubics="!-1220 335(;-1107,805 -1034,1111 -999,1253q-1220 335Q-1052 1040q-999 1253);"/>
                    <Edge cubics="!-921 3(;-922,1 -922,-1 -923,-2q-921 3Q-922 0q-923 -2);"/>
                    <Edge cubics="!-1154 260(;-1117,142 -1063,63 -994,24q-1154 260Q-1098 83q-994 24);"/>
                    <Edge cubics="!-699 2254(;-689,2277 -678,2298 -667,2319q-699 2254Q-684 2288q-667 2319);"/>
                    <Edge cubics="!-758 2095(;-740,2154 -720,2207 -699,2254q-758 2095Q-730 2183q-699 2254);"/>
                    <Edge cubics="!-994 24(;-994,24 -586,1427 -586,1427q-994 24 -586 1427);"/>
                    <Edge cubics="!-1154 260(;-1042,62 -934,518 -830,1629q-1154 260Q-986 -37q-830 1629);"/>
                    <Edge cubics="!-435 2203(;-471,2337 -533,2351 -621,2246q-435 2203Q-489 2404q-621 2246);"/>
                    <Edge cubics="!-830 1629(;-672,1930 -603,2136 -621,2246q-830 1629Q-593 2081q-621 2246);"/>
                    <Edge cubics="!-586 1427(;-518,2026 -467,2285 -435,2203q-586 1427Q-484 2326q-435 2203);"/>
                    <Edge cubics="!-994 -169(;-994,-169 -1068,-202 -1068,-202q-994 -169 -1068 -202);"/>
                    <Edge cubics="!-1068 -202(;-1143,-202 -1198,-159 -1232,-74q-1068 -202Q-1180 -202q-1232 -74);"/>
                  </edges>
                </DOMShape>
              </elements>
            </DOMFrame>
          </frames>
        </DOMLayer>
      </layers>
    </DOMTimeline>
  </timeline>
</DOMSymbolItem>