<DOMSymbolItem xmlns:xsi="http://www.w3.org/2001/XMLSchema-instance" xmlns="http://ns.adobe.com/xfl/2008/" name="shape/Symbol 3006" itemID="6597607e-00000de3" symbolType="graphic" lastModified="1704196122">
  <timeline>
    <DOMTimeline name="Symbol 3006">
      <layers>
        <DOMLayer name="Layer_1" color="#4F4FFF" current="true" isSelected="true">
          <frames>
            <DOMFrame index="0" motionTweenScale="false" keyMode="8192">
              <elements>
                <DOMShape isFloating="true">
                  <fills>
                    <FillStyle index="1">
                      <SolidColor color="#444444"/>
                    </FillStyle>
                  </fills>
                  <strokes>
                    <StrokeStyle index="1">
                      <SolidStroke scaleMode="normal">
                        <fill>
                          <SolidColor/>
                        </fill>
                      </SolidStroke>
                    </StrokeStyle>
                    <StrokeStyle index="2">
                      <SolidStroke scaleMode="normal">
                        <fill>
                          <SolidColor/>
                        </fill>
                      </SolidStroke>
                    </StrokeStyle>
                  </strokes>
                  <edges>
                    <Edge fillStyle1="1" strokeStyle="1" edges="!1684 0|1658 1802!1658 1802[1415 1954 1307 1733!1307 1733|1266 24"/>
                    <Edge strokeStyle="2" edges="!1266 24|1242 25"/>
                    <Edge fillStyle1="1" strokeStyle="2" edges="!1266 24|1684 0"/>
                  </edges>
                </DOMShape>
              </elements>
            </DOMFrame>
          </frames>
        </DOMLayer>
        <DOMLayer name="Layer_2" color="#4F4FFF">
          <frames>
            <DOMFrame index="0" motionTweenScale="false" keyMode="8192">
              <elements>
                <DOMShape isFloating="true">
                  <fills>
                    <FillStyle index="1">
                      <SolidColor color="#444444"/>
                    </FillStyle>
                  </fills>
                  <strokes>
                    <StrokeStyle index="1">
                      <SolidStroke scaleMode="normal">
                        <fill>
                          <SolidColor/>
                        </fill>
                      </SolidStroke>
                    </StrokeStyle>
                    <StrokeStyle index="2">
                      <SolidStroke scaleMode="normal">
                        <fill>
                          <SolidColor/>
                        </fill>
                      </SolidStroke>
                    </StrokeStyle>
                  </strokes>
                  <edges>
                    <Edge strokeStyle="1" edges="!1302 544|1322 496"/>
                    <Edge fillStyle1="1" strokeStyle="2" edges="!1302 544|1299 551"/>
                    <Edge fillStyle1="1" strokeStyle="1" edges="!1299 551[1122 943 862 1016"/>
                    <Edge fillStyle1="1" strokeStyle="2" edges="!862 1016[431 994 0 861!0 861|166 636!166 636[415 800 867 831!867 831[1094 655 1337 371!1337 371|1302 544"/>
                  </edges>
                </DOMShape>
              </elements>
            </DOMFrame>
          </frames>
        </DOMLayer>
        <DOMLayer name="Layer_3" color="#4F4FFF">
          <frames>
            <DOMFrame index="0" motionTweenScale="false" keyMode="8192">
              <elements>
                <DOMShape isFloating="true">
                  <fills>
                    <FillStyle index="1">
                      <SolidColor color="#444444"/>
                    </FillStyle>
                  </fills>
                  <strokes>
                    <StrokeStyle index="1">
                      <SolidStroke scaleMode="normal">
                        <fill>
                          <SolidColor/>
                        </fill>
                      </SolidStroke>
                    </StrokeStyle>
                  </strokes>
                  <edges>
                    <Edge fillStyle0="1" strokeStyle="1" edges="!1030 2147|1077 1633!1077 1633|952 1648!952 1648|917 2229"/>
                    <Edge fillStyle0="1" fillStyle1="1" strokeStyle="1" edges="!917 2229[964 2090 1030 2147"/>
                    <Edge fillStyle0="1" strokeStyle="1" edges="!917 2229|1643 2886!1643 2886|1668 2714!1668 2714|1030 2147"/>
                    <Edge strokeStyle="1" edges="!1643 2886|1653 2895"/>
                  </edges>
                </DOMShape>
              </elements>
            </DOMFrame>
          </frames>
        </DOMLayer>
        <DOMLayer name="Layer_4" color="#4F4FFF">
          <frames>
            <DOMFrame index="0" motionTweenScale="false" keyMode="8192">
              <elements>
                <DOMShape isFloating="true">
                  <fills>
                    <FillStyle index="1">
                      <SolidColor color="#444444"/>
                    </FillStyle>
                  </fills>
                  <strokes>
                    <StrokeStyle index="1">
                      <SolidStroke scaleMode="normal">
                        <fill>
                          <SolidColor/>
                        </fill>
                      </SolidStroke>
                    </StrokeStyle>
                    <StrokeStyle index="2">
                      <SolidStroke scaleMode="normal">
                        <fill>
                          <SolidColor/>
                        </fill>
                      </SolidStroke>
                    </StrokeStyle>
                  </strokes>
                  <edges>
                    <Edge fillStyle1="1" strokeStyle="2" edges="!2063 411|2192 524"/>
                    <Edge fillStyle0="1" fillStyle1="1" strokeStyle="2" edges="!2192 524|989 1754"/>
                    <Edge fillStyle0="1" strokeStyle="2" edges="!989 1754|1063 1759!1063 1759|2317 635!2317 635|2192 524!961 1618[909 1732 989 1754"/>
                    <Edge fillStyle1="1" strokeStyle="1" edges="!961 1618|2063 411"/>
                  </edges>
                </DOMShape>
              </elements>
            </DOMFrame>
          </frames>
        </DOMLayer>
        <DOMLayer name="Layer_5" color="#4F4FFF">
          <frames>
            <DOMFrame index="0" motionTweenScale="false" keyMode="8192">
              <elements>
                <DOMShape isFloating="true">
                  <fills>
                    <FillStyle index="1">
                      <SolidColor color="#444444"/>
                    </FillStyle>
                  </fills>
                  <strokes>
                    <StrokeStyle index="1">
                      <SolidStroke scaleMode="normal">
                        <fill>
                          <SolidColor/>
                        </fill>
                      </SolidStroke>
                    </StrokeStyle>
                    <StrokeStyle index="2">
                      <SolidStroke scaleMode="normal">
                        <fill>
                          <SolidColor/>
                        </fill>
                      </SolidStroke>
                    </StrokeStyle>
                  </strokes>
                  <edges>
                    <Edge fillStyle1="1" strokeStyle="2" edges="!1378 1743|1557 1737!1557 1737|1667 1733!1667 1733|1667 2319"/>
                    <Edge fillStyle0="1" fillStyle1="1" strokeStyle="2" edges="!1667 2319|1667 2344"/>
                    <Edge strokeStyle="1" edges="!1378 1743|1377 1718"/>
                    <Edge fillStyle0="1" strokeStyle="2" edges="!1526 2523|1587 2875!1587 2875|1988 2579!1988 2579|1667 2319"/>
                    <Edge fillStyle1="1" strokeStyle="1" edges="!1410 2344|1401 2330!1401 2330|1378 1743"/>
                    <Edge fillStyle1="1" strokeStyle="2" edges="!1526 2523|1410 2344"/>
                    <Edge fillStyle0="1" fillStyle1="1" strokeStyle="2" edges="!1667 2319|1557 2404!1557 2404|1526 2523!1557 1737|1557 2404"/>
                  </edges>
                </DOMShape>
              </elements>
            </DOMFrame>
          </frames>
        </DOMLayer>
      </layers>
    </DOMTimeline>
  </timeline>
</DOMSymbolItem>