<DOMSymbolItem xmlns:xsi="http://www.w3.org/2001/XMLSchema-instance" xmlns="http://ns.adobe.com/xfl/2008/" name="1.特效文件夹/10.力大砖飞/强烈地爆/未命名文件夹 1/Symbol 5211" itemID="65536bc5-0000293c" lastModified="1698481640">
  <timeline>
    <DOMTimeline name="Symbol 5211">
      <layers>
        <DOMLayer name="Layer 1" color="#A551B9" current="true" isSelected="true">
          <frames>
            <DOMFrame index="0" keyMode="9728">
              <elements>
                <DOMShape isFloating="true">
                  <fills>
                    <FillStyle index="1">
                      <SolidColor/>
                    </FillStyle>
                    <FillStyle index="2">
                      <RadialGradient>
                        <matrix>
                          <Matrix a="0.0191650390625" d="0.0191650390625" tx="13" ty="11.05"/>
                        </matrix>
                        <GradientEntry color="#9C8D81" ratio="0"/>
                        <GradientEntry color="#716756" ratio="1"/>
                      </RadialGradient>
                    </FillStyle>
                    <FillStyle index="3">
                      <RadialGradient>
                        <matrix>
                          <Matrix a="0.0260009765625" d="0.0260009765625" tx="9.9" ty="35.2"/>
                        </matrix>
                        <GradientEntry color="#716756" ratio="0"/>
                        <GradientEntry color="#141313" ratio="1"/>
                      </RadialGradient>
                    </FillStyle>
                  </fills>
                  <edges>
                    <Edge fillStyle1="1" edges="!421 230|423 232!423 232|473 295!473 295|524 355!524 355|513 426!513 426|503 553!503 553|498 561!498 561|425 687!425 687|355 802!355 802|274 902!274 902|260 921!260 921[187 861 100 846!100 846|76 793!76 793|23 450!23 450|9 301!9 301|0
 226!0 226|74 170!74 170[132 122 169 75!169 75|176 75!176 75[210 75 262 42!262 42|419 227!419 227|421 230"/>
                    <Edge fillStyle0="1" fillStyle1="2" edges="
!412 312|409 312!409 312|428 327!428 327|446 334!446 334|412 312!457 307|455 306!455 306[469 320 481 349!481 349|480 351!480 351|483 372!483 372[452 549 436 549!436 549|361 538!361 538[322 528 309 515!309 515[288 508 277 492!277 492[270
 481 268 463!268 463[244 431 222 367!222 367|189 244!189 244|189 242!189 242|186 237!186 237|184 228!184 228|325 287!325 287|314 274!314 274|285 231!285 231|246 191!246 191[216 159 216 151!216 151[216 136 225 138!225 138|228 117!228 117
[228 101 251 95!251 95[274 89 294 102!294 102[306 111 327 143!327 143|357 189!357 189|447 294!447 294|457 307!246 218|190 203!190 203|204 181!204 181|246 218"/>
                    <Edge fillStyle0="1" fillStyle1="3" edges="
!183 291[198 323 198 342!198 342|207 373!207 373|215 398!215 398|236 458!236 458|257 524!257 524[181 559 83 728!83 728|82 718!82 718|70 609!70 609[70 526 51 391!51 391|31 265!31 265[31 244 48 244!48 244|134 249!134 249[163 249 183 291"/>
                    <Edge fillStyle0="1" fillStyle1="2" edges="
!334 271|331 267!331 267|322 257!322 257|316 251!316 251|338 276!338 276|334 271!337 300|337 299!337 299|336 299!336 299|337 300"/>
                    <Edge fillStyle0="1" fillStyle1="3" edges="
!272 594[246 615 244 626!244 626|216 631!216 631|174 651!174 651|177 645!177 645[190 618 229 573!229 573|261 538!261 538|272 594"/>
                    <Edge fillStyle0="3" fillStyle1="1" edges="
!260 649|171 673!171 673|161 672!161 672|90 754!90 754|87 754!87 754[92 771 102 786!102 786[135 838 213 838!213 838[233 838 255 744!255 744|273 652!273 652|260 649"/>
                  </edges>
                </DOMShape>
              </elements>
            </DOMFrame>
          </frames>
        </DOMLayer>
      </layers>
    </DOMTimeline>
  </timeline>
</DOMSymbolItem>