{
    "$SIDE_TITLE_10001": "末世残缺的经济",
    "$SIDE_DESCRIPTION_10001": "（该支线要求先通过主线任务“学习技能”）找理发师∞天ㄙ★使的剪∞谈谈，理发师位于基地左侧楼梯口处，酒吧大门旁。",
    "$SIDE_GET_10001": [
        {
            "name": "$PC",
            "title": "$PC_TITLE",
            "char": "$PC_CHAR",
            "text": "shop姐，现在打扰不要紧吧？"
        },
        {
            "name": "Shop Girl",
            "title": "军火商",
            "char": "Shop Girl#微笑",
            "text": "没什么问题，而且也不需要对我这么客气。对我而言做生意还是要避免居高临下的处境，这会让自己飘飘然的。"
        },
        {
            "name": "$PC",
            "title": "$PC_TITLE",
            "char": "$PC_CHAR",
            "text": "好的。我是想问，还有没有物资搜集工作需要我来做？因为，几个罐头就能让blue哥教我技能，我想这种冒险的工作回报还是很不错的。"
        },
        {
            "name": "Shop Girl",
            "title": "军火商",
            "char": "Shop Girl#微笑",
            "text": "量力而行吧菜鸟，你现在可不能保证每次都能从人类敌人的袭击下活着回来。"
        },
        {
            "name": "Shop Girl",
            "title": "军火商",
            "char": "Shop Girl#微笑",
            "text": "而且，我也不能过于频繁地接收你们的货物。我对大部分来我这里接受任务的佣兵都提过要求，不要向我一次性大量出售货物，最好分批次少量出售。"
        },
        {
            "name": "$PC",
            "title": "$PC_TITLE",
            "char": "$PC_CHAR",
            "text": "这是为什么？"
        },
        {
            "name": "Shop Girl",
            "title": "军火商",
            "char": "Shop Girl#思考",
            "text": "如你所见，我的确是个武器贩子。但是末世的环境，尤其是A兵团的现实需要，我也不得不兼顾一些经济方面的工作。"
        },
        {
            "name": "Shop Girl",
            "title": "军火商",
            "char": "Shop Girl",
            "text": "具体而言，我要确保A兵团的物资流通和货币价值保持一个相对稳定的对应状态，短时间内大量物资的涌入会让货币系统崩溃的。"
        },
        {
            "name": "Shop Girl",
            "title": "军火商",
            "char": "Shop Girl",
            "text": "末世里也没什么专业的经济机构了，我也只能通过这种粗暴的限制流动的方法来稳定币值了。"
        },
        {
            "name": "$PC",
            "title": "$PC_TITLE",
            "char": "$PC_CHAR",
            "text": "好吧··虽然我不是很理解，不过政府发行的货币早已成废纸了吧，现在的货币我只知道是金属，但是价格是怎么算的呢？"
        },
        {
            "name": "Shop Girl",
            "title": "军火商",
            "char": "Shop Girl#微笑",
            "text": "哦，你为什么不自己去亲自体验一下呢？找一楼的理发师谈谈价格吧，也顺便把你有末日气息的头发整理一下。"
        }
       ],
    "$SIDE_FINISH_10001": [
         
    ],
    "$SIDE_TITLE_10002": "福利",
    "$SIDE_DESCRIPTION_10002": "（该支线要求先通过支线任务“末世残缺的经济”）找Shop Girl谈谈。",
    "$SIDE_GET_10002": [
        {
            "name": "∞天ㄙ★使的剪∞",
            "title": "理发师",
            "char": "∞天ㄙ★使的剪∞",
            "text": "欢迎！想剪什么发型呢？"
        },
        {
            "name": "$PC",
            "title": "$PC_TITLE",
            "char": "$PC_CHAR#微笑",
            "text": "你觉得怎么好看就怎么办吧。"
        },
        {
            "name": "∞天ㄙ★使的剪∞",
            "title": "理发师",
            "char": "∞天ㄙ★使的剪∞",
            "text": "末日里最合适的当然是清爽的发型，不过比较复杂的也不错，“讲究格调”可是A兵团的特征。"
        },
        {
            "name": "$PC",
            "title": "$PC_TITLE",
            "char": "$PC_CHAR#微笑",
            "text": "理发要多少钱？"
        },
        {
            "name": "∞天ㄙ★使的剪∞",
            "title": "理发师",
            "char": "∞天ㄙ★使的剪∞",
            "text": "前些天还是要钱的，不过最近老大把花费免了。"
        },
        {
            "name": "$PC",
            "title": "$PC_TITLE",
            "char": "$PC_CHAR",
            "text": "不收钱，那你的工资就由A兵团包了？"
        },
        {
            "name": "∞天ㄙ★使的剪∞",
            "title": "理发师",
            "char": "∞天ㄙ★使的剪∞",
            "text": "是这样的，不过这也是因为我和老大认识也有段时间了。他以前叫拼命之王的时候，经常在我那家“XX发廊”外和人打架。"
        },
        {
            "name": "$PC",
            "title": "$PC_TITLE",
            "char": "$PC_CHAR",
            "text": "叉叉发廊？我听说叉叉是一个重工集团的名字，好像是隶属于3xf巨型企业的。"
        },
        {
            "name": "∞天ㄙ★使的剪∞",
            "title": "理发师",
            "char": "∞天ㄙ★使的剪∞",
            "text": "其实那些年管的没那么严，名字蹭一蹭热度也不是大问题。他们叫叉叉，而我这是字母的XX，一般人会混用，自然我们这就有名气了。"
        },
        {
            "name": "$PC",
            "title": "$PC_TITLE",
            "char": "$PC_CHAR",
            "text": "它们没找你麻烦？"
        },
        {
            "name": "∞天ㄙ★使的剪∞",
            "title": "理发师",
            "char": "∞天ㄙ★使的剪∞",
            "text": "当年C国版权和商标号保护不严嘛，哪像后来，什么名字后面都得跟一个™·····"
        }
    ],
    "$SIDE_FINISH_10002": [
    ],
    "$SIDE_TITLE_10003": "农产品出口",
    "$SIDE_DESCRIPTION_10003": "（该支线要求先通过支线任务“福利”）找Shop Girl谈谈。",
    "$SIDE_GET_10003": [
        {
            "name": "$PC",
            "title": "$PC_TITLE",
            "char": "$PC_CHAR",
            "text": "所以说，shop姐，理发师说理发不要钱，这似乎也没有展示什么物价啊。"
        },
        {
            "name": "Shop Girl",
            "title": "军火商",
            "char": "Shop Girl#微笑",
            "text": "那我给你读一读这份文件·······本月内勤补助费占总开支的6%，数额环比增长162%。"
        },
        {
            "name": "Shop Girl",
            "title": "军火商",
            "char": "Shop Girl#微笑",
            "text": "这个是理发免费的代价，而这份代价要出在别的地方。我们A兵团本就不像军阀，坐拥庞大的军火产业，无论进口还是手工生产热兵器的成本都不低，再加上基地对内补助后需要收支平衡，于是你看到我这里的武器的价格了吧？"
        },
        {
            "name": "$PC",
            "title": "$PC_TITLE",
            "char": "$PC_CHAR",
            "text": "既然如此，为什么还要给理发补助？"
        },
        {
            "name": "Shop Girl",
            "title": "军火商",
            "char": "Shop Girl#微笑",
            "text": "我们A兵团说到底讲究一个团结，这是我们的发展之基。通过这种开销来提升士气、稳定人心当然是再好不过的。实际上，在我们攻下这座监狱之初，暴力内讧也不少见，现在则基本销声匿迹了。"
        },
        {
            "name": "$PC",
            "title": "$PC_TITLE",
            "char": "$PC_CHAR",
            "text": "这个就是末世前政府经常提的福利政策，是吧？"
        },
        {
            "name": "Shop Girl",
            "title": "军火商",
            "char": "Shop Girl#思考",
            "text": "正如政府的福利政策被财政保守派讥讽为“养懒汉”一样，我们A兵团这种策略也被西区堕落城很多人说是末世里精致小姑娘的胭脂粉。"
        },
        {
            "name": "Shop Girl",
            "title": "军火商",
            "char": "Shop Girl#思考",
            "text": "我们会提供免费理发，会发放一些卫生物品，也会维护地下水水质。这些都是有代价的，如果这种福利政策把握得好，对我们来说自然是大有好处。"
        },
        {
            "name": "Shop Girl",
            "title": "军火商",
            "char": "Shop Girl",
            "text": "当然，反过来说，政府的福利政策把握不好，也会因为收支平衡问题造成其他领域补贴不足或者收税太重，进而在产业转型中落入下风。我们A兵团也是因此长期被视为武力羸弱的势力。"
        },
        {
            "name": "$PC",
            "title": "$PC_TITLE",
            "char": "$PC_CHAR",
            "text": "你们一定想过对策吧？"
        },
        {
            "name": "Shop Girl",
            "title": "军火商",
            "char": "Shop Girl#微笑",
            "text": "没错。而且告诉你也无妨，你早晚会知道。我们A兵团有农产品出口。"
        },
        {
            "name": "$PC",
            "title": "$PC_TITLE",
            "char": "$PC_CHAR#微笑",
            "text": "哦哦，难道是末世初期就有流传的禁区粮食车队？"
        },
        {
            "name": "Shop Girl",
            "title": "军火商",
            "char": "Shop Girl#微笑",
            "text": "消息挺灵通嘛。就是如此，正因为我们有粮食出口，才能相对维持收支平衡，并且同时进口一些热兵器，也给我们控制下的产业进行一定的补助。我们高层实力比较强，其他势力或许轻视我们的组织度，但也未必敢贸然进攻。"
        },
        {
            "name": "Shop Girl",
            "title": "军火商",
            "char": "Shop Girl#微笑",
            "text": "总之就是如此，A兵团的经济体制也就如此，不过相比于土匪经济，还是好上不少的。"
        }
        ],
  "$SIDE_FINISH_10003": [
        {
            "name": "Shop Girl",
            "title": "军火商",
            "char": "Shop Girl#微笑",
            "text": "我们A兵团对废城的经营还是比较上心的，也比较照顾废城外围的小势力。你解决了废城第一防线的丧尸潮问题，我就给你安排其他任务。"
        }
  ],
    "$SIDE_TITLE_10004": "公社求援",
    "$SIDE_DESCRIPTION_10004": "（该支线要求先通过主线任务“尸群”与支线任务“农产品出口”）找Shop Girl谈谈。",
    "$SIDE_GET_10004": [
        {
            "name": "Shop Girl",
            "title": "军火商",
            "char": "Shop Girl#微笑",
            "text": "啊，看来这件应该说挺重要的事情需要麻烦你。"
        },
        {
            "name": "$PC",
            "title": "$PC_TITLE",
            "char": "$PC_CHAR",
            "text": "没问题。"
        },
        {
            "name": "Shop Girl",
            "title": "军火商",
            "char": "Shop Girl#微笑",
            "text": "挺自信啊，那也是好事。是这样的，蓉都公社派人来向我们求援，希望我们对郊区进行清扫。"
        },
        {
            "name": "Shop Girl",
            "title": "军火商",
            "char": "Shop Girl#微笑",
            "text": "这个蓉都公社主要是末世前的农民和工人组成的。审判日前几个月，尘都市区的化肥厂和钢铁厂搬迁到了郊区，那些工人也转移到那里去了。末世中这些人就和本地农民组成同盟了。"
        },
        {
            "name": "$PC",
            "title": "$PC_TITLE",
            "char": "$PC_CHAR",
            "text": "这么说，他们的农业挺厉害吧？"
        },
        {
            "name": "Shop Girl",
            "title": "军火商",
            "char": "Shop Girl#微笑",
            "text": "的确，不过他们虽然有化肥，但是总体上缺水。毕竟他们没有控制地下水，而且工业与农业生产都要耗水，末世中很难厚此薄彼。"
        },
        {
            "name": "Shop Girl",
            "title": "军火商",
            "char": "Shop Girl",
            "text": "总之，最近郊区的盗贼和丧尸越来越多了，看起来不像是自然聚集的，我怀疑是西区的盗贼团体有意识向废城扩张，他们的行动也吸引了不少丧尸。"
        },
        {
            "name": "Shop Girl",
            "title": "军火商",
            "char": "Shop Girl",
            "text": "废城很大程度上是我们的势力范围，我们挡住了丧尸的进攻，也占有大部分废城的潜在资源。这些盗贼不但想从我们这分一杯羹，还对其他废城外围的势力造成威胁。各种角度来说，都需要给他们教训了。"
        },
        {
            "name": "Shop Girl",
            "title": "军火商",
            "char": "Shop Girl#微笑",
            "text": "明白吧？让他们有损失，或者至少是把丧尸清理了，这样那些废城势力还能放开手脚对付盗贼。"
        },
        {
            "name": "Shop Girl",
            "title": "军火商",
            "char": "Shop Girl#微笑",
            "text": "要让不分敌我的势力们意识到：废城是A兵团的自留地。"
        }
    ],
    "$SIDE_FINISH_10004": [
    ],
    "$SIDE_TITLE_10005": "性产业管制",
    "$SIDE_DESCRIPTION_10005": "（该支线要求先通过支线任务“公社求援”）找格格巫谈谈。",
    "$SIDE_GET_10005": [
        {
            "name": "Shop Girl",
            "title": "军火商",
            "char": "Shop Girl#微笑",
            "text": "不错哦，正好蓉都公社送来了谢礼，你先收着吧。"
        },
        {
            "name": "$PC",
            "title": "$PC_TITLE",
            "char": "$PC_CHAR#微笑",
            "text": "这么多吗？"
        },
        {
            "name": "Shop Girl",
            "title": "军火商",
            "char": "Shop Girl#微笑",
            "text": "那些人还是能造一些弹药的，虽然质量不佳，不过末世里能用就不错了。"
        },
        {
            "name": "Shop Girl",
            "title": "军火商",
            "char": "Shop Girl",
            "text": "啊对，正好有件事需要你帮忙。"
        },
        {
            "name": "$PC",
            "title": "$PC_TITLE",
            "char": "$PC_CHAR",
            "text": "是什么事？"
        },
        {
            "name": "Shop Girl",
            "title": "军火商",
            "char": "Shop Girl",
            "text": "其实我们A兵团内部有性产业。末日之后秩序崩塌，我们根本没法约束这种事情，只能尽量进行管制来避免性病扩散。尽管如此，最近医务室也传来了不妙的病例统计，显示性病发病率越来越高了。"
        },
        {
            "name": "Shop Girl",
            "title": "军火商",
            "char": "Shop Girl",
            "text": "我这里只有简略的报告结果，缺少详细资料，得从格格巫那里去问。但是我们兵团内一直有人对这方面产业持开放态度，被他们发现我去医务室，很容易就能根据我的过往发言猜到我打算对这方面限制了，会给我造成压力。"
        },
        {
            "name": "Shop Girl",
            "title": "军火商",
            "char": "Shop Girl",
            "text": "你的话没太大问题，平常只是作为战斗人员行动，不会被怀疑的。做事小心点，和格格巫谨慎交谈，别被人发现。做好后也给你奖励。"
        },
        {
            "name": "$PC",
            "title": "$PC_TITLE",
            "char": "$PC_CHAR",
            "text": "好的。"
        }
    ],
    "$SIDE_FINISH_10005": [
    ],
    "$SIDE_TITLE_10010": "医务室风险",
    "$SIDE_DESCRIPTION_10010": "（该支线要求先通过支线任务“性产业管制”）找Shop Girl谈谈。",
    "$SIDE_GET_10010": [
        {
            "name": "$PC",
            "title": "$PC_TITLE",
            "char": "$PC_CHAR",
            "text": "格格巫医生，打扰了，我有些问题想问你。"
        },
        {
            "name": "格格巫",
            "title": "医生",
            "char": "格格巫",
            "text": "稍等······好，你有什么问题？"
        },
        {
            "name": "$PC",
            "title": "$PC_TITLE",
            "char": "$PC_CHAR",
            "text": "shop姐···shopgirl托我来问你，关于性病发病率的问题。"
        },
        {
            "name": "格格巫",
            "title": "医生",
            "char": "格格巫",
            "text": "我得说情况比资料里轻描淡写的内容复杂得多。为了让恐慌情绪不扩散，资料的写法是受到限制的。实际上，这一个月因为有明显性病而来这里就医的佣兵，就已经有几十多个，已经有我新栽培的助理在手术时不慎感染了。"
        },
        {
            "name": "$PC",
            "title": "$PC_TITLE",
            "char": "$PC_CHAR",
            "text": "那该怎么办呢？"
        },
        {
            "name": "格格巫",
            "title": "医生",
            "char": "格格巫",
            "text": "指望我们医生肯定是不行了，我们没法解决源头的问题。不过来我这治病的佣兵的确经常提到酒吧的那个舞女，或许这是你们的突破口吧。"
        },
        {
            "name": "$PC",
            "title": "$PC_TITLE",
            "char": "$PC_CHAR",
            "text": "我知道了，感谢你的回答。"
        }
    ],
    "$SIDE_FINISH_10010": [
    ],
    "$SIDE_TITLE_10011": "谨慎限制",
    "$SIDE_DESCRIPTION_10011": "（该支线要求先通过支线任务“医务室风险”）找舞女谈谈。",
    "$SIDE_GET_10011": [
        {
            "name": "$PC",
            "title": "$PC_TITLE",
            "char": "$PC_CHAR",
            "text": "简单来说，医务室那边记录的一个月的性病发病数到了两位数以上，感染了医护人员。格格巫认为佣兵们提到的那个舞女可能有办法解决这件事情。"
        },
        {
            "name": "Shop Girl",
            "title": "军火商",
            "char": "Shop Girl",
            "text": "酒吧的舞女吗···这可不好解决。她和酒保都是堕落城来的，因为能力出众所以被允许留下。酒保是擅长经营酒吧以及有情报来源，而舞女则是能够在我们的监管下整合所有性交易渠道，避免暗藏的、我们管不到的性交易太多。"
        },
        {
            "name": "Shop Girl",
            "title": "军火商",
            "char": "Shop Girl#严肃",
            "text": "别看她平常一副谄媚的样子，经营的能力恐怕不比我差，只不过我卖的是军火·····"
        },
        {
            "name": "Shop Girl",
            "title": "军火商",
            "char": "Shop Girl",
            "text": "那么，我待会从流动资金那里申请一批特殊资金，用来购置避孕和性安全用品，你去跟舞女说一下，让她配合给她管的人分发这些东西，具体时间我会另外找机会告诉她。还有就是让她管教一下那些乱搞的手下人。"
        },
        {
            "name": "$PC",
            "title": "$PC_TITLE",
            "char": "$PC_CHAR",
            "text": "安全用品···这种东西也有吗？"
        },
        {
            "name": "Shop Girl",
            "title": "军火商",
            "char": "Shop Girl",
            "text": "本来我也不干这个的，但是现在这种局势，我也只能把这些也包办了。"
        }
    ],
    "$SIDE_FINISH_10011": [
    ],
    "$SIDE_TITLE_10012": "公营桃色",
    "$SIDE_DESCRIPTION_10012": "（该支线要求先通过支线任务“医务室风险”）找Shop Girl谈谈。",
    "$SIDE_GET_10012": [
        {
            "name": "$PC",
            "title": "$PC_TITLE",
            "char": "$PC_CHAR",
            "text": "嗯···这位小姐，shopgirl派我来告诉你一些事。"
        },
        {
            "name": "舞女",
            "title": "身体艺术家",
            "char": "舞女",
            "text": "哦，是什么事呢？"
        },
        {
            "name": "$PC",
            "title": "$PC_TITLE",
            "char": "$PC_CHAR",
            "text": "她申请了一批资金用来购入避孕用品之类的，希望你配合分发，具体时间她会再派人来说。以及她希望你能管教一下手下人的行为。"
        },
        {
            "name": "舞女",
            "title": "身体艺术家",
            "char": "舞女",
            "text": "这样吗？好吧，我会给那些人一些教训的。"
        },
        {
            "name": "$PC",
            "title": "$PC_TITLE",
            "char": "$PC_CHAR",
            "text": "···可以问一问是要干什么吗？"
        },
        {
            "name": "舞女",
            "title": "身体艺术家",
            "char": "舞女",
            "text": "我们行业的规矩而已，你还是不要了解太多了。"
        },
        {
            "name": "舞女",
            "title": "身体艺术家",
            "char": "舞女",
            "text": "倒是你，对我们行业服务不感兴趣吗？男女服务可是都有的。"
        },
        {
            "name": "$PC",
            "title": "$PC_TITLE",
            "char": "$PC_CHAR",
            "text": "还是不了···"
        },
        {
            "name": "舞女",
            "title": "身体艺术家",
            "char": "舞女",
            "text": "是吗？我想shopgirl应该说了不少有关我的坏话。你把那些话全当真就不合适了。再怎么说，我们这些人也是给A兵团交税的，而且你们上面的人也不是不参与···我们姑且也算公立机构了。"
        },
        {
            "name": "$PC",
            "title": "$PC_TITLE",
            "char": "$PC_CHAR",
            "text": "好的。不过我还有事，先告辞了···"
        }
    ],
    "$SIDE_FINISH_10012": [
        {
            "name": "Shop Girl",
            "title": "军火商",
            "char": "Shop Girl",
            "text": "医疗从技术上应付了疾病问题，而问题的根源在于政治···因此，在一片肮脏中处理人与人的利益关系，是解决这性病问题的必经之路。"
        },
        {
            "name": "Shop Girl",
            "title": "军火商",
            "char": "Shop Girl",
            "text": "就是这样，你明白我的难处了吧。"
        },
        {
            "name": "$PC",
            "title": "$PC_TITLE",
            "char": "$PC_CHAR",
            "text": "确实，这个位子不是谁都能坐的。"
        },
        {
            "name": "Shop Girl",
            "title": "军火商",
            "char": "Shop Girl",
            "text": "我也是第一次管卫生这方面的管理工作，这些在审判日前是政府卫生部门的官员负责的。真是···麻烦啊。"
        },
        {
            "name": "Shop Girl",
            "title": "军火商",
            "char": "Shop Girl#微笑",
            "text": "不过，你做的好，真让我省心。这些奖励你拿着吧，以后有什么好的工作我还会找你的。"
        },
        {
            "name": "Shop Girl",
            "title": "军火商",
            "char": "Shop Girl#微笑",
            "text": "这笔钱也记在公共卫生支出上了，算差遣费。"
        },
        {
            "name": "$PC",
            "title": "$PC_TITLE",
            "char": "$PC_CHAR",
            "text": "听起来很正规啊。"
        },
        {
            "name": "Shop Girl",
            "title": "军火商",
            "char": "Shop Girl#微笑",
            "text": "我们要建立秩序，必须不断变得正规。卫生部该有的，我们早晚也会有。"
        }
    ],
    "$SIDE_TITLE_10013": "净水试剂及其效果",
    "$SIDE_DESCRIPTION_10013": "（该支线要求先通过主线任务“息事宁人”以及支线任务“公营桃色”）找格格巫谈谈。",
    "$SIDE_GET_10013": [
        {
            "name": "Shop Girl",
            "title": "军火商",
            "char": "Shop Girl",
            "text": "那么，现在我们算是处理掉那些频繁打扰我们的盗贼了。"
        },
        {
            "name": "$PC",
            "title": "$PC_TITLE",
            "char": "$PC_CHAR",
            "text": "但是，只要堕落城乱下去，我们就不可能摆脱这种情况吧？"
        },
        {
            "name": "Shop Girl",
            "title": "军火商",
            "char": "Shop Girl",
            "text": "的确如此。不过，对我们来说，一个强权把持整个堕落城是更加危险的。如果要维持当前的外交方针，那么势力错综复杂的堕落城对我们来说就是必要的抓手。"
        },
        {
            "name": "Shop Girl",
            "title": "军火商",
            "char": "Shop Girl",
            "text": "这不意味着我们要接受现状。我们得换个思路，拉拢一部分盗贼。盗贼不过是一群乌合之众的统称，没有什么真正意义上的领袖，不过的确有一些零散的头目。"
        },
        {
            "name": "Shop Girl",
            "title": "军火商",
            "char": "Shop Girl",
            "text": "我尝试和一部分盗贼进行谈判，他们的确也想和我们达成和平，不过需要一些条件。这些条件不算苛刻，而且他们和我们达成和平后要面对其他零散盗贼势力的劫掠，付出的代价也不小。"
        },
        {
            "name": "Shop Girl",
            "title": "军火商",
            "char": "Shop Girl",
            "text": "总之，从谈判内容来看，这些盗贼需要一些净水材料，而我们正好有一批明矾。"
        },
        {
            "name": "$PC",
            "title": "$PC_TITLE",
            "char": "$PC_CHAR",
            "text": "净水？"
        },
        {
            "name": "Shop Girl",
            "title": "军火商",
            "char": "Shop Girl#微笑",
            "text": "不是每个势力都像我们一样有地下水的。想从污染水源中提取能喝的水，光煮沸也不够，一些化学试剂也是必需的。"
        },
        {
            "name": "$PC",
            "title": "$PC_TITLE",
            "char": "$PC_CHAR",
            "text": "户外的净水···已经稀缺到这种地步了？"
        },
        {
            "name": "Shop Girl",
            "title": "军火商",
            "char": "Shop Girl",
            "text": "嘛···污染是一方面，还有就是，这些盗贼也根本不懂如何保存试剂，再加上战乱频繁，从我们这里获取稳定的药剂来源也就自然而然了。"
        },
        {
            "name": "Shop Girl",
            "title": "军火商",
            "char": "Shop Girl#微笑",
            "text": "总之呢，这些净水试剂由格格巫进行保管，你去跟他说明一下情况。那些盗贼会对此表达感激的。"
        }
    ],
    "$SIDE_FINISH_10013": [
    ],
    "$SIDE_TITLE_10014": "材料净水的秘密",
    "$SIDE_DESCRIPTION_10014": "（该支线要求先通过支线任务“净水试剂及其效果”）找Shop Girl谈谈。",
    "$SIDE_GET_10014": [
        {
            "name": "格格巫",
            "title": "医生",
            "char": "格格巫",
            "text": "所以，你需要明矾作为净水材料？"
        },
        {
            "name": "$PC",
            "title": "$PC_TITLE",
            "char": "$PC_CHAR",
            "text": "是的，shop姐委托我来的。"
        },
        {
            "name": "格格巫",
            "title": "医生",
            "char": "格格巫",
            "text": "净水材料有很多种，不过看样子，shopgirl的想法不是那么简单啊···"
        },
        {
            "name": "$PC",
            "title": "$PC_TITLE",
            "char": "$PC_CHAR",
            "text": "什么意思？"
        },
        {
            "name": "格格巫",
            "title": "医生",
            "char": "格格巫",
            "text": "明矾不是最好的净水材料，它长期来看对于人体是有毒害的，因为铝离子···算了，不说这个。"
        },
        {
            "name": "格格巫",
            "title": "医生",
            "char": "格格巫",
            "text": "毕竟交易对象是盗贼，而且shopgirl也是为组织着想，我也不好多说什么。"
        },
        {
            "name": "$PC",
            "title": "$PC_TITLE",
            "char": "$PC_CHAR",
            "text": "···"
        },
        {
            "name": "格格巫",
            "title": "医生",
            "char": "格格巫",
            "text": "这里是目前可以提供的明矾，你先给shopgirl拿去。还有相当多分量是作为和其他势力谈判的筹码，一时间不好拿出太多。"
        }
    ],
    "$SIDE_FINISH_10014": [
        {
            "name": "$PC",
            "title": "$PC_TITLE",
            "char": "$PC_CHAR",
            "text": "这是格格巫托我送来的明矾。"
        },
        {
            "name": "Shop Girl",
            "title": "军火商",
            "char": "Shop Girl",
            "text": "比想象的要少···不过没事，那些盗贼也没法再讨价还价了。"
        },
        {
            "name": "$PC",
            "title": "$PC_TITLE",
            "char": "$PC_CHAR",
            "text": "对了，shop姐，这些明矾打发给盗贼，真的合适吗？"
        },
        {
            "name": "Shop Girl",
            "title": "军火商",
            "char": "Shop Girl",
            "text": "明矾算是我们这里储备最多、价值相对最低的净水材料了。如果能够稳住形势，那么小组织也是可以储存一批明矾的。只不过盗贼这种吃了上顿没下顿的货色非常欠缺这种材料，才会来找我们获取这个。"
        },
        {
            "name": "Shop Girl",
            "title": "军火商",
            "char": "Shop Girl",
            "text": "当然，我们的确有不少其他材料，不过，你懂的吧，材料往往代表了技术。"
        },
        {
            "name": "$PC",
            "title": "$PC_TITLE",
            "char": "$PC_CHAR",
            "text": "技术？"
        },
        {
            "name": "Shop Girl",
            "title": "军火商",
            "char": "Shop Girl#微笑",
            "text": "你啊，要不是你已经完全是A兵团的人了，我才不会和你说这些好猜的事情。"
        },
        {
            "name": "Shop Girl",
            "title": "军火商",
            "char": "Shop Girl#微笑",
            "text": "如果我们这里有大量更好的工业级净水材料流出，很快其他势力就会开始猜测我们的工业运转情况了。"
        },
        {
            "name": "$PC",
            "title": "$PC_TITLE",
            "char": "$PC_CHAR",
            "text": "这样吗？"
        },
        {
            "name": "Shop Girl",
            "title": "军火商",
            "char": "Shop Girl#微笑",
            "text": "对于末世后脆弱的局势来说，情报战也是战斗的一环，我们在这条战线上也不能懈怠啊。"
        },
        {
            "name": "Shop Girl",
            "title": "军火商",
            "char": "Shop Girl#微笑",
            "text": "我已经很信任你了，所以才会跟你说这些，可不要让我失望啊。"
        },
        {
            "name": "$PC",
            "title": "$PC_TITLE",
            "char": "$PC_CHAR",
            "text": "明白。"
        },
        {
            "name": "Shop Girl",
            "title": "军火商",
            "char": "Shop Girl#微笑",
            "text": "我会把这批明矾交给盗贼的，感谢你的帮助。"
        },
        {
            "name": "$PC",
            "title": "$PC_TITLE",
            "char": "$PC_CHAR",
            "text": "我感觉我只是传了话、送了货而已吧。"
        },
        {
            "name": "Shop Girl",
            "title": "军火商",
            "char": "Shop Girl#微笑",
            "text": "了解组织的实际情况当然也是贡献啦···总之，继续努力吧。"
        }
    ],
    "$SIDE_TITLE_10015": "公社外交使节",
    "$SIDE_DESCRIPTION_10015": "（该支线要求先通过主线任务“不安之影”以及支线任务“材料净水的秘密”）找幸存老兵谈谈。",
    "$SIDE_GET_10015": [
        {
            "name": "Shop Girl",
            "title": "军火商",
            "char": "Shop Girl",
            "text": "比起盗贼，我们更需要注意的是其他较为强大且底线更高的势力。他们往往更能收拢人心，比目光短浅的盗贼潜力更大。"
        },
        {
            "name": "$PC",
            "title": "$PC_TITLE",
            "char": "$PC_CHAR",
            "text": "大厅里的那些人，看起来不像是佣兵，他们就是那些势力派来的外交人员吗？"
        },
        {
            "name": "Shop Girl",
            "title": "军火商",
            "char": "Shop Girl#微笑",
            "text": "不错。这次我打算把那个幸存老兵介绍给你。"
        },
        {
            "name": "$PC",
            "title": "$PC_TITLE",
            "char": "$PC_CHAR",
            "text": "对方的名字是？"
        },
        {
            "name": "Shop Girl",
            "title": "军火商",
            "char": "Shop Girl#微笑",
            "text": "不太清楚什么原因，总之，他不愿意透露自己的姓名。不过，可以确定的是他代表蓉都公社来这里进行外交工作。"
        },
        {
            "name": "Shop Girl",
            "title": "军火商",
            "char": "Shop Girl",
            "text": "你应该记得，之前你帮助公社那边清理了郊区的尸潮，对方为表感激，给你送来了大量弹药。"
        },
        {
            "name": "$PC",
            "title": "$PC_TITLE",
            "char": "$PC_CHAR",
            "text": "不过，他们的实力恐怕不强。郊区的丧尸并不算多，但已经让他们觉得棘手了。"
        },
        {
            "name": "Shop Girl",
            "title": "军火商",
            "char": "Shop Girl",
            "text": "嘛，我之前也是这么想的，直到他们送给你那些弹药。不要小看这点，能够稳定产出弹药的势力绝对不容小觑，只要给他们更多训练时间，或许他们能成长为足以和更强大势力抗衡的阵营。"
        },
        {
            "name": "$PC",
            "title": "$PC_TITLE",
            "char": "$PC_CHAR",
            "text": "也就是说，他们可能在未来对我们有威胁？"
        },
        {
            "name": "Shop Girl",
            "title": "军火商",
            "char": "Shop Girl",
            "text": "至少现在不会，我们目前还需要团结小势力，为了这点可能性就葬送外交形象，乃至于损害当前的利益，可不一定是划算的买卖。"
        },
        {
            "name": "Shop Girl",
            "title": "军火商",
            "char": "Shop Girl",
            "text": "说回正题。把你介绍给他们，也是为了先拉近我们和他们之间的关系。他们看起来长期缺乏稳定的资源来源和精英士兵，空有工业机械却难以运转，而如果你作为一个帮他们解决了燃眉之急的人···"
        },
        {
            "name": "$PC",
            "title": "$PC_TITLE",
            "char": "$PC_CHAR",
            "text": "那么，就会以我为代表，拉高A兵团在他们那边的形象。"
        },
        {
            "name": "Shop Girl",
            "title": "军火商",
            "char": "Shop Girl#微笑",
            "text": "并且让他们在产业上依赖我们。先去会会那个幸存老兵吧。"
        }
    ],
    "$SIDE_FINISH_10015": [
    ],
    "$SIDE_TITLE_10016": "科学造物？",
    "$SIDE_DESCRIPTION_10016": "（该支线要求先通过支线任务“公社外交使节”），通关修罗难度AVP，然后找幸存老兵谈谈。AVP可从幸存老兵处通过获取任务进入",
    "$SIDE_GET_10016": [
        {
            "name": "$PC",
            "title": "$PC_TITLE",
            "char": "$PC_CHAR",
            "text": "我是代表A兵团来，与公社外交使节进行交流的代表。"
        },
        {
            "name": "幸存老兵",
            "title": "猎人",
            "char": "幸存老兵",
            "text": "您好。"
        },
        {
            "name": "$PC",
            "title": "$PC_TITLE",
            "char": "$PC_CHAR",
            "text": "客气了。"
        },
        {
            "name": "幸存老兵",
            "title": "猎人",
            "char": "幸存老兵",
            "text": "我来这里是为了向贵方寻求支援，我们需要获取南方森林的木材，然而森林里到处都是可怖的生物。"
        },
        {
            "name": "$PC",
            "title": "$PC_TITLE",
            "char": "$PC_CHAR",
            "text": "如果只是丧尸的话，恐怕不至于让你这么说。"
        },
        {
            "name": "幸存老兵",
            "title": "猎人",
            "char": "幸存老兵",
            "text": "的确，森林里的怪物，它们在堕落城一般被称为“异形”以及“铁血战士”，据说是沿袭自某个电影系列的名字。"
        },
        {
            "name": "$PC",
            "title": "$PC_TITLE",
            "char": "$PC_CHAR#严肃",
            "text": "电影的内容能成真吗？"
        },
        {
            "name": "幸存老兵",
            "title": "猎人",
            "char": "幸存老兵",
            "text": "我当然不相信电影里的东西会到现实世界，但科学造物就不同了。"
        },
        {
            "name": "幸存老兵",
            "title": "猎人",
            "char": "幸存老兵",
            "text": "尘都这片地方，以前是3xf统治的，他们很早就开始进行生物研究了。据说三战期间，他们就出动了生物武器。据目击者透露，这种生物武器外形非常像电影里的生物。或许这就是这些怪物得到这种名字的原因。"
        },
        {
            "name": "$PC",
            "title": "$PC_TITLE",
            "char": "$PC_CHAR",
            "text": "这恐怕不是偶然吧？"
        },
        {
            "name": "幸存老兵",
            "title": "猎人",
            "char": "幸存老兵",
            "text": "我不了解这些内容的细节。总之，如果你帮我们暂时消灭森林里的怪物，我方必有谢礼。"
        },
        {
            "name": "$PC",
            "title": "$PC_TITLE",
            "char": "$PC_CHAR",
            "text": "没问题。"
        }
    ],
    "$SIDE_FINISH_10016": [
    ],
    "$SIDE_TITLE_10017": "工业原料",
    "$SIDE_DESCRIPTION_10017": "（该支线要求先通过支线任务“科学造物？”）找Shop Girl谈谈。",
    "$SIDE_GET_10017": [
        {
            "name": "$PC",
            "title": "$PC_TITLE",
            "char": "$PC_CHAR",
            "text": "那些怪物已经被我杀了。"
        },
        {
            "name": "幸存老兵",
            "title": "猎人",
            "char": "幸存老兵",
            "text": "感谢。除了药剂和钱之外，我们目前能够给你的还有这批铝粉。"
        },
        {
            "name": "$PC",
            "title": "$PC_TITLE",
            "char": "$PC_CHAR",
            "text": "我可能暂时用不上。"
        },
        {
            "name": "幸存老兵",
            "title": "猎人",
            "char": "幸存老兵",
            "text": "我听闻贵方有载具频繁出动，又需要新建分基地，这些铝粉可以给你们的燃料工业以及建筑工业不小的帮助。"
        },
        {
            "name": "$PC",
            "title": "$PC_TITLE",
            "char": "$PC_CHAR",
            "text": "看来你对我方的工业水平了解不少。"
        },
        {
            "name": "幸存老兵",
            "title": "猎人",
            "char": "幸存老兵",
            "text": "只是猜测。不过，我方还需要请求一件事。"
        },
        {
            "name": "$PC",
            "title": "$PC_TITLE",
            "char": "$PC_CHAR",
            "text": "什么事情？"
        },
        {
            "name": "幸存老兵",
            "title": "猎人",
            "char": "幸存老兵",
            "text": "我们的生产工作需要一些碱液和酸液，如果贵方可以拿出的话，我方感激不尽。"
        },
        {
            "name": "$PC",
            "title": "$PC_TITLE",
            "char": "$PC_CHAR",
            "text": "好的。"
        }
    ],
    "$SIDE_FINISH_10017": [
    ],
    "$SIDE_TITLE_10018": "腐蚀物库存",
    "$SIDE_DESCRIPTION_10018": "（该支线要求先通过支线任务“工业原料”）找小F谈谈。",
    "$SIDE_GET_10018": [
        {
            "name": "Shop Girl",
            "title": "军火商",
            "char": "Shop Girl#微笑",
            "text": "大概情况我了解了。这些铝粉我们暂时倒不算用得着，你跑腿一番也挺累的，就当是给你的额外报酬吧。"
        },
        {
            "name": "$PC",
            "title": "$PC_TITLE",
            "char": "$PC_CHAR",
            "text": "多谢。"
        },
        {
            "name": "Shop Girl",
            "title": "军火商",
            "char": "Shop Girl",
            "text": "至于说碱液和酸液，我对此的了解不算细致，需要问专门人员了。小F和丽丽丝的研究工作都需要用到这些，你先去问问小F，如果我们的库存足够的话，给公社那边一点好处也可以。"
        }
    ],
    "$SIDE_FINISH_10018": [
    ],
    "$SIDE_TITLE_10019": "制药研究",
    "$SIDE_DESCRIPTION_10019": "（该支线要求先通过支线任务“腐蚀物库存”）找丽丽丝谈谈。",
    "$SIDE_GET_10019": [
        {
            "name": "小F",
            "title": "机械师",
            "char": "小F",
            "text": "我们这里碱液储备还算充足，酸液前阵子被丽丽丝申请调用了，大概是用于制药方面的研究。你去找她问。"
        },
        {
            "name": "$PC",
            "title": "$PC_TITLE",
            "char": "$PC_CHAR",
            "text": "了解了。"
        },
        {
            "name": "小F",
            "title": "机械师",
            "char": "小F",
            "text": "我可提醒你一句，和她说话要小心点。"
        },
        {
            "name": "$PC",
            "title": "$PC_TITLE",
            "char": "$PC_CHAR",
            "text": "什么意思？"
        },
        {
            "name": "小F",
            "title": "机械师",
            "char": "小F",
            "text": "她脾气可不算好啊，尤其是对我。"
        },
        {
            "name": "$PC",
            "title": "$PC_TITLE",
            "char": "$PC_CHAR",
            "text": "···我知道了。"
        }
    ],
    "$SIDE_FINISH_10019": [
    ],
    "$SIDE_TITLE_10020": "储备尚可",
    "$SIDE_DESCRIPTION_10020": "（该支线要求先通过支线任务“制药研究”）找Shop Girl谈谈。",
    "$SIDE_GET_10020": [
        {
            "name": "丽丽丝",
            "title": "护士",
            "char": "丽丽丝",
            "text": "什么事？"
        },
        {
            "name": "$PC",
            "title": "$PC_TITLE",
            "char": "$PC_CHAR",
            "text": "shop姐让我来询问酸液的库存，如果充足的话，我们会给公社那边一些支援。"
        },
        {
            "name": "丽丽丝",
            "title": "护士",
            "char": "丽丽丝",
            "text": "不算多，但还有点库存。弱酸缺口挺大的，强酸倒是剩了不少，这有点王水你可以送去。"
        },
        {
            "name": "$PC",
            "title": "$PC_TITLE",
            "char": "$PC_CHAR",
            "text": "好···"
        },
        {
            "name": "丽丽丝",
            "title": "护士",
            "char": "丽丽丝",
            "text": "···看着我干什么？"
        },
        {
            "name": "$PC",
            "title": "$PC_TITLE",
            "char": "$PC_CHAR",
            "text": "我听人说你脾气不好，不过感觉并非如此。"
        },
        {
            "name": "丽丽丝",
            "title": "护士",
            "char": "丽丽丝",
            "text": "肯定是小F说的吧，不要听那家伙瞎说。看来他又想吃针头了。"
        },
        {
            "name": "$PC",
            "title": "$PC_TITLE",
            "char": "$PC_CHAR",
            "text": "···我先回去汇报情况了"
        }
    ],
    "$SIDE_FINISH_10020": [
    ],
    "$SIDE_TITLE_10021": "药物支援",
    "$SIDE_DESCRIPTION_10021": "（该支线要求先通过支线任务“储备尚可”）找幸存老兵谈谈。",
    "$SIDE_GET_10021": [
        {
            "name": "Shop Girl",
            "title": "军火商",
            "char": "Shop Girl",
            "text": "看起来没问题了，那么，给对面送礼吧。"
        },
        {
            "name": "$PC",
            "title": "$PC_TITLE",
            "char": "$PC_CHAR",
            "text": "shop姐，小F和丽丽丝的关系很差吗？"
        },
        {
            "name": "Shop Girl",
            "title": "军火商",
            "char": "Shop Girl",
            "text": "还好吧，他们两个有些相似之处。"
        },
        {
            "name": "$PC",
            "title": "$PC_TITLE",
            "char": "$PC_CHAR",
            "text": "都很有技术实力。"
        },
        {
            "name": "Shop Girl",
            "title": "军火商",
            "char": "Shop Girl",
            "text": "这的确是一方面···闲话少说，把这些东西给公社代表送过去吧。"
        }
    ],
    "$SIDE_FINISH_10021": [
    ],
    "$SIDE_TITLE_10022": "芳香精油",
    "$SIDE_DESCRIPTION_10022": "（该支线要求先通过支线任务“药物支援”）找Shop Girl谈谈。",
    "$SIDE_GET_10022": [
        {
            "name": "幸存老兵",
            "title": "猎人",
            "char": "幸存老兵",
            "text": "感谢，除了金钱外，这批精油也请收下。"
        },
        {
            "name": "$PC",
            "title": "$PC_TITLE",
            "char": "$PC_CHAR",
            "text": "这是什么，化妆品？"
        },
        {
            "name": "幸存老兵",
            "title": "猎人",
            "char": "幸存老兵",
            "text": "从植物还有动物中提取的，不单单是化妆品，大部分还是用来做调味料和香薰的。"
        },
        {
            "name": "$PC",
            "title": "$PC_TITLE",
            "char": "$PC_CHAR",
            "text": "我明白了。"
        }
    ],
    "$SIDE_FINISH_10022": [
        {
            "name": "$PC",
            "title": "$PC_TITLE",
            "char": "$PC_CHAR",
            "text": "shop姐，这是对面送来的精油。"
        },
        {
            "name": "Shop Girl",
            "title": "军火商",
            "char": "Shop Girl#微笑",
            "text": "哦，刻意和我说这个，是想讨我开心吗？"
        },
        {
            "name": "$PC",
            "title": "$PC_TITLE",
            "char": "$PC_CHAR",
            "text": "这种礼物的用途应该由shop姐决断吧。"
        },
        {
            "name": "Shop Girl",
            "title": "军火商",
            "char": "Shop Girl#微笑",
            "text": "我就不需要这种了，就算是用化妆品，直接用工业精油还是太浪费了，拿去装点我们基地也比妆点我更合适。"
        },
        {
            "name": "Shop Girl",
            "title": "军火商",
            "char": "Shop Girl#微笑",
            "text": "这些你就自己留着吧，以后帮我做事，这些好处肯定少不了你。"
        }
    ]
}