<DOMSymbolItem xmlns:xsi="http://www.w3.org/2001/XMLSchema-instance" xmlns="http://ns.adobe.com/xfl/2008/" name="Symbol 585" itemID="6577efbc-00000422" symbolType="graphic" lastModified="1702098593">
  <timeline>
    <DOMTimeline name="Symbol 585">
      <layers>
        <DOMLayer name="Layer 1" color="#4F4FFF" current="true" isSelected="true">
          <frames>
            <DOMFrame index="0" motionTweenScale="false" keyMode="8192">
              <elements>
                <DOMShape isFloating="true">
                  <fills>
                    <FillStyle index="1">
                      <SolidColor color="#333333"/>
                    </FillStyle>
                    <FillStyle index="2">
                      <SolidColor/>
                    </FillStyle>
                  </fills>
                  <strokes>
                    <StrokeStyle index="1">
                      <SolidStroke scaleMode="normal">
                        <fill>
                          <SolidColor/>
                        </fill>
                      </SolidStroke>
                    </StrokeStyle>
                  </strokes>
                  <edges>
                    <Edge fillStyle1="1" strokeStyle="1" edges="!37 173[-86 11 -208 -183!-208 -183[-152 -224 -97 -266!-97 -266[31 -56 140 97"/>
                    <Edge fillStyle1="2" strokeStyle="1" edges="!140 97|209 190!209 190|109 267!109 267|37 173"/>
                    <Edge fillStyle0="1" fillStyle1="2" edges="!37 173|140 97"/>
                  </edges>
                </DOMShape>
              </elements>
            </DOMFrame>
          </frames>
        </DOMLayer>
      </layers>
    </DOMTimeline>
  </timeline>
</DOMSymbolItem>