<DOMSymbolItem xmlns:xsi="http://www.w3.org/2001/XMLSchema-instance" xmlns="http://ns.adobe.com/xfl/2008/" name="lochan/lo-chan呆毛" itemID="66bf6782-00000208" lastModified="1723819906">
  <timeline>
    <DOMTimeline name="lo-chan呆毛">
      <layers>
        <DOMLayer name="图层_1" color="#00FFFF" current="true" isSelected="true">
          <frames>
            <DOMFrame index="0" keyMode="9728">
              <elements>
                <DOMShape>
                  <fills>
                    <FillStyle index="1">
                      <SolidColor/>
                    </FillStyle>
                    <FillStyle index="2">
                      <SolidColor color="#7A648E"/>
                    </FillStyle>
                  </fills>
                  <strokes>
                    <StrokeStyle index="1">
                      <SolidStroke scaleMode="normal" weight="0.5">
                        <fill>
                          <SolidColor/>
                        </fill>
                      </SolidStroke>
                    </StrokeStyle>
                  </strokes>
                  <edges>
                    <Edge fillStyle0="1" fillStyle1="2" edges="!182 196S3[181 195 179 195!179 195[177 195 176 197!176 197[128 264 120 371!120 371[116 411 118 458!118 458[62 403 36 357!36 357[-3 291 18 241!18 241[18 239 18 237!18 237[17 235 15 235!15 235|14 234"/>
                    <Edge fillStyle1="2" strokeStyle="1" edges="!14 234S6[36 -35 556 5!556 5[245 72 182 196"/>
                    <Edge fillStyle1="1" edges="!182 196S2|183 196!183 196[184 197 185 199!185 199[185 201 184 203!184 203[138 268 130 372!130 372[125 417 129 470!129 470|129 473!129 473[128 474 126 475!126 475[125 475 123 475!123 475[122 475 121 474!121 474[118 472 117 470!117 470
[55 411 27 362!27 362[26 360 25 359!25 359[-13 292 7 240!7 240[8 239 9 237!9 237[9 235 11 235!11 235[12 234 14 234"/>
                    <Edge cubics="!18 241(;18,240 18,238 18,237q18 241Q18 239q18 237);"/>
                    <Edge cubics="!18 237(;17,236 16,235 15,235q18 237Q17 235q15 235);"/>
                    <Edge cubics="!15 235(;15,235 14,234 14,234q15 235 14 234);"/>
                    <Edge cubics="!9 237(;8,238 8,239 7,240q9 237Q8 239q7 240);"/>
                    <Edge cubics="!11 235(;10,235 9,236 9,237q11 235Q9 235q9 237);"/>
                    <Edge cubics="!14 234(;13,234 12,234 11,235q14 234Q12 234q11 235);"/>
                    <Edge cubics="!184 203(;185,202 185,200 185,199q184 203Q185 201q185 199);"/>
                    <Edge cubics="!185 199(;184,198 184,197 183,196q185 199Q184 197q183 196);"/>
                    <Edge cubics="!182 196(;181,195 180,195 179,195q182 196Q181 195q179 195);"/>
                    <Edge cubics="!183 196(;183,196 183,196 182,196q183 196Q183 196q182 196);"/>
                    <Edge cubics="!179 195(;178,195 177,196 176,197q179 195Q177 195q176 197);"/>
                    <Edge cubics="!120 371(;117,398 117,427 118,458q120 371Q116 411q118 458);"/>
                    <Edge cubics="!126 475(;127,474 128,474 129,473q126 475Q128 474q129 473);"/>
                    <Edge cubics="!117 470(;118,471 119,473 121,474q117 470Q118 472q121 474);"/>
                    <Edge cubics="!121 474(;122,475 122,475 123,475q121 474Q122 475q123 475);"/>
                    <Edge cubics="!123 475(;124,475 125,475 126,475q123 475Q125 475q126 475);"/>
                    <Edge cubics="!129 470(;126,435 127,402 130,372q129 470Q125 417q130 372);"/>
                    <Edge cubics="!25 359(;26,360 26,361 27,362q25 359Q26 360q27 362);"/>
                    <Edge cubics="!118 458(;81,421 53,388 36,357q118 458Q62 403q36 357);"/>
                    <Edge cubics="!27 362(;46,395 76,431 117,470q27 362Q55 411q117 470);"/>
                    <Edge cubics="!36 357(;10,313 4,274 18,241q36 357Q-3 291q18 241);"/>
                    <Edge cubics="!7 240(;-6,275 0,314 25,359q7 240Q-13 292q25 359);"/>
                    <Edge cubics="!130 372(;135,303 153,246 184,203q130 372Q138 268q184 203);"/>
                    <Edge cubics="!176 197(;144,242 125,300 120,371q176 197Q128 264q120 371);"/>
                    <Edge cubics="!556 5(;349,50 224,113 182,196q556 5Q245 72q182 196);"/>
                    <Edge cubics="!14 234(;29,55 209,-22 556,5q14 234Q36 -35q556 5);"/>
                    <Edge cubics="!129 473(;129,473 129,470 129,470q129 473 129 470);"/>
                  </edges>
                </DOMShape>
              </elements>
            </DOMFrame>
          </frames>
        </DOMLayer>
      </layers>
    </DOMTimeline>
  </timeline>
</DOMSymbolItem>