[
  {
    "level": 1,
    "name": "艾米",
    "id": 230,
    "height": 165,
    "face": 0,
    "hair": 27,
    "gender": "女",
    "equipment": {
      "head": "黑框眼镜",
      "body": "红黑色功夫装",
      "hand": "白色手套",
      "leg": "黑灰色紧身裤",
      "foot": "黑色白底皮鞋",
      "neck": "新手军牌",
      "primary": null,
      "secondary1": "PPK",
      "secondary2": "PPK",
      "melee": "pencil",
      "grenade": "普通手雷"
    }
  },
  {
    "level": 3,
    "name": "李想",
    "id": 231,
    "height": 173,
    "face": 0,
    "hair": 23,
    "gender": "女",
    "equipment": {
      "head": null,
      "body": "黑灰色深V紧身衣#2",
      "hand": null,
      "leg": "SM女王吊带袜#2",
      "foot": "黑色高跟皮鞋#2",
      "neck": "新手军牌#2",
      "primary": null,
      "secondary1": null,
      "secondary2": null,
      "melee": "匕首#2",
      "grenade": null
    },
    "pricemultiplier": 0.7,
    "passive":{
      "口才":{"技能名":"口才", "等级":1, "启用":true}
    }
  },
  {
    "level": 1,
    "name": "蓝环酱",
    "id": 5611,
    "height": 150,
    "face": 0,
    "hair": 28,
    "gender": "女",
    "equipment": {
      "head": "科技潜入头盔",
      "body": "黑白女仆装",
      "hand": "科技潜入手套",
      "leg": "黑白女仆蕾丝短裙",
      "foot": "黑色白底皮鞋",
      "neck": "一颗章鱼球",
      "primary": "一把奇怪的尤克里里",
      "secondary1": "应援棒",
      "secondary2": "应援棒",
      "melee": null,
      "grenade": null
    },
    "pricemultiplier": 0.3,
    "hidden": true
  },
  {
    "level": 2,
    "name": "克里斯",
    "id": 232,
    "height": 160,
    "face": 0,
    "hair": 26,
    "gender": "女",
    "equipment": {
      "head": "红色风镜",
      "body": "新手衣服",
      "hand": "白色手套",
      "leg": "黑灰色紧身裤",
      "foot": "黑色白底皮鞋",
      "neck": "新手军牌",
      "primary": null,
      "secondary1": null,
      "secondary2": "PPK",
      "melee": "匕首",
      "grenade": null
    }
  },
  {
    "level": 3,
    "name": "奥斯",
    "id": 233,
    "height": 172,
    "face": 1,
    "hair": 35,
    "gender": "男",
    "equipment": {
      "head": null,
      "body": "新手衣服",
      "hand": null,
      "leg": "黑色西装裤",
      "foot": null,
      "neck": "新手军牌",
      "primary": null,
      "secondary1": "m9",
      "secondary2": "m9",
      "melee": "匕首",
      "grenade": null
    }
  },
  {
    "level": 4,
    "name": "科斯",
    "id": 234,
    "height": 172,
    "face": 1,
    "hair": 17,
    "gender": "男",
    "equipment": {
      "head": "盗贼猪鼻式防毒面具",
      "body": "盗贼无袖皮马甲",
      "hand": null,
      "leg": "盗贼牛仔裤带腿包",
      "foot": "黑色白底皮鞋",
      "neck": "新手军牌",
      "primary": null,
      "secondary1": "M1911",
      "secondary2": null,
      "melee": "水管",
      "grenade": null
    }
  },
  {
    "level": 5,
    "name": "杰克",
    "id": 235,
    "height": 170,
    "face": 1,
    "hair": 35,
    "gender": "男",
    "equipment": {
      "head": "黑色X蒙面",
      "body": "褐色皮衣",
      "hand": "牛皮手套",
      "leg": "金色腰带破洞牛仔裤",
      "foot": "红色功夫布鞋",
      "neck": "新手军牌",
      "primary": "L85A1",
      "secondary1": "M1911",
      "secondary2": "M1911",
      "melee": "水管",
      "grenade": null
    }
  },
  {
    "level": 6,
    "name": "比特",
    "id": 236,
    "height": 175,
    "face": 1,
    "hair": 17,
    "gender": "男",
    "equipment": {
      "head": "红外线滤光镜",
      "body": "黑色功夫高手装",
      "hand": null,
      "leg": "白色功夫高手裤子",
      "foot": "黑色功夫布鞋",
      "neck": "僵尸割草机军牌",
      "primary": "L85A1",
      "secondary1": "M1911",
      "secondary2": "M1911",
      "melee": "水管",
      "grenade": null
    }
  },
  {
    "level": 7,
    "name": "高枝雪",
    "id": 237,
    "height": 160,
    "face": 0,
    "hair": 28,
    "gender": "女",
    "equipment": {
      "head": null,
      "body": "白色短袖校服",
      "hand": "白色手套",
      "leg": "红色百褶短裙",
      "foot": "黑色白底皮鞋",
      "neck": "僵尸割草机军牌",
      "primary": "L85A1",
      "secondary1": "M1911",
      "secondary2": "M1911",
      "melee": "美式警棍",
      "grenade": "普通手雷"
    }
  },
  {
    "level": 10,
    "name": "血手",
    "id": 238,
    "height": 181,
    "face": 1,
    "hair": 35,
    "gender": "男",
    "equipment": {
      "head": "沙漠军装头盔",
      "body": "沙漠军装背心",
      "hand": "弗莱迪手套",
      "leg": "沙漠军装裤",
      "foot": "沙漠军装皮鞋",
      "neck": "僵尸割草机军牌",
      "primary": "L85A1",
      "secondary1": "UZI",
      "secondary2": "UZI",
      "melee": "美式警棍",
      "grenade": "普通手雷"
    }
  },
  {
    "level": 9,
    "name": "鹏",
    "id": 239,
    "height": 172,
    "face": 1,
    "hair": 14,
    "gender": "男",
    "equipment": {
      "head": "警用防爆服头盔",
      "body": "警用防爆服背心",
      "hand": "黑色皮手套",
      "leg": "警用防爆服裤",
      "foot": "褐色厚底皮鞋",
      "neck": "僵尸割草机军牌",
      "primary": "L85A1",
      "secondary1": "UZI",
      "secondary2": "UZI",
      "melee": "棒球棒",
      "grenade": null
    }
  },
  {
    "level": 8,
    "name": "赵明",
    "id": 240,
    "height": 170,
    "face": 1,
    "hair": 35,
    "gender": "男",
    "equipment": {
      "head": "黑色摩托头盔",
      "body": "军绿防弹衣",
      "hand": "黑色皮手套",
      "leg": "墨绿军用下装",
      "foot": "墨绿军用鞋",
      "neck": "新手军牌",
      "primary": "AK47",
      "secondary1": "Mp5 pdw",
      "secondary2": "Mp5 pdw",
      "melee": "锤子",
      "grenade": "普通手雷"
    }
  },
  {
    "level": 10,
    "name": "雄鹰",
    "id": 23239,
    "height": 175,
    "face": 1,
    "hair": 14,
    "gender": "男",
    "equipment": {
      "head": "战术猪鼻式防毒面具",
      "body": "A兵团制式战术背心",
      "hand": "A兵团制式战术手套",
      "leg": "A兵团制式战术裤",
      "foot": "A兵团制式战术皮鞋",
      "neck": "A兵团项链",
      "primary": "M4A1",
      "secondary1": "Mp5 pdw",
      "secondary2": "Mp5 pdw",
      "melee": "战术狗腿刀",
      "grenade": "普通手雷"
    }
  },
  {
    "level": 11,
    "name": "血梅",
    "id": 23250,
    "height": 167,
    "face": 0,
    "hair": 23,
    "gender": "女",
    "equipment": {
      "head": "战术猪鼻式防毒面具",
      "body": "A兵团制式战术背心",
      "hand": "A兵团制式战术手套",
      "leg": "A兵团制式战术裤",
      "foot": "A兵团制式战术皮鞋",
      "neck": "A兵团项链",
      "primary": "M4A1",
      "secondary1": "MP7",
      "secondary2": "MP7",
      "melee": "战术狗腿刀",
      "grenade": "普通手雷"
    }
  },
  {
    "level": 11,
    "name": "雷霆",
    "id": 241,
    "height": 170,
    "face": 1,
    "hair": 14,
    "gender": "男",
    "equipment": {
      "head": null,
      "body": "褐色皮带装",
      "hand": "道钉手套",
      "leg": "墨绿军用下装",
      "foot": "墨绿军用鞋",
      "neck": "僵尸割草机军牌",
      "primary": "AK47",
      "secondary1": "MP7",
      "secondary2": "MP7",
      "melee": "破旧的军刀",
      "grenade": "普通手雷"
    }
  },
  {
    "level": 12,
    "name": "Alex",
    "id": 242,
    "height": 185,
    "face": 1,
    "hair": 35,
    "gender": "男",
    "equipment": {
      "head": "黑色X蒙面",
      "body": "军绿防弹衣",
      "hand": "黑色皮手套",
      "leg": "墨绿军用下装",
      "foot": "墨绿军用鞋",
      "neck": "守护者军牌",
      "primary": "AK47",
      "secondary1": "MP7",
      "secondary2": "MP7",
      "melee": "战术狗腿刀",
      "grenade": null
    }
  },
  {
    "level": 13,
    "name": "血月",
    "id": 243,
    "height": 177,
    "face": 1,
    "hair": 35,
    "gender": "男",
    "equipment": {
      "head": "黑色X蒙面",
      "body": "军绿防弹衣",
      "hand": "黑色皮手套",
      "leg": "墨绿军用下装",
      "foot": "墨绿军用鞋",
      "neck": "守护者军牌",
      "primary": "M4A1",
      "secondary1": "MP7",
      "secondary2": "MP7",
      "melee": "战术狗腿刀",
      "grenade": null
    }
  },
  {
    "level": 13,
    "name": "武卫",
    "id": 244,
    "height": 168,
    "face": 0,
    "hair": 21,
    "gender": "女",
    "equipment": {
      "head": "战术猪鼻式防毒面具",
      "body": "红黑色功夫装",
      "hand": "科技潜入手套",
      "leg": "黑色功夫短裤",
      "foot": "科技潜入靴",
      "neck": "A兵团项链",
      "primary": "UMP",
      "secondary1": "MP7",
      "secondary2": "MP7",
      "melee": "单刀",
      "grenade": "普通手雷"
    }
  },
  {
    "level": 14,
    "name": "Rachel",
    "id": 245,
    "height": 171,
    "face": 1,
    "hair": 16,
    "gender": "男",
    "equipment": {
      "head": null,
      "body": "褐色皮衣",
      "hand": "黑色皮手套",
      "leg": "棕色带腿包短裤",
      "foot": "红色功夫布鞋",
      "neck": "守护者军牌",
      "primary": "UMP",
      "secondary1": "MP7",
      "secondary2": "MP7",
      "melee": "拆迁铁锤",
      "grenade": null
    }
  },
  {
    "level": 15,
    "name": "锋刃",
    "id": 23248,
    "height": 180,
    "face": 1,
    "hair": 35,
    "gender": "男",
    "equipment": {
      "head": "战术猪鼻式防毒面具",
      "body": "A兵团制式战术背心",
      "hand": "A兵团制式战术手套",
      "leg": "A兵团制式战术裤",
      "foot": "A兵团制式战术皮鞋",
      "neck": "A兵团项链",
      "primary": "UMP",
      "secondary1": "MP7",
      "secondary2": "MP7",
      "melee": "大剑",
      "grenade": "普通手雷"
    }
  },
  {
    "level": 16,
    "name": "熊大",
    "id": 246,
    "height": 170,
    "face": 1,
    "hair": 35,
    "gender": "男",
    "equipment": {
      "head": "双色巧克力味小熊头",
      "body": "双色巧克力味小熊上装",
      "hand": "双色巧克力味小熊手套",
      "leg": "双色巧克力味小熊下装",
      "foot": "双色巧克力味小熊鞋",
      "neck": "守护者军牌",
      "primary": "XM8",
      "secondary1": "Mossberg500",
      "secondary2": "Mossberg500",
      "melee": "双面斧",
      "grenade": "普通手雷"
    }
  },
  {
    "level": 15,
    "name": "烈焰",
    "id": 247,
    "height": 170,
    "face": 1,
    "hair": 35,
    "gender": "男",
    "equipment": {
      "head": "黑色X蒙面",
      "body": "黑灰色连帽马甲",
      "hand": "A兵团制式战术手套",
      "leg": "黑色功夫短裤",
      "foot": "红色功夫布鞋",
      "neck": "守护者军牌",
      "primary": "吉他喷火器",
      "secondary1": null,
      "secondary2": null,
      "melee": "砍刀",
      "grenade": null
    }
  },
  {
    "level": 18,
    "name": "荒狼",
    "id": 248,
    "height": 181,
    "face": 1,
    "hair": 2,
    "gender": "男",
    "equipment": {
      "head": "战术猪鼻式防毒面具",
      "body": "A兵团制式战术背心",
      "hand": "A兵团制式战术手套",
      "leg": "A兵团制式战术裤",
      "foot": "A兵团制式战术皮鞋",
      "neck": "A兵团项链",
      "primary": "XM1014",
      "secondary1": "P90",
      "secondary2": "P90",
      "melee": "大剑",
      "grenade": "普通手雷"
    }
  },
  {
    "level": 18,
    "name": "死神",
    "id": 249,
    "height": 179,
    "face": 1,
    "hair": 8,
    "gender": "男",
    "equipment": {
      "head": "战术猪鼻式防毒面具",
      "body": "A兵团制式战术背心",
      "hand": "A兵团制式战术手套",
      "leg": "A兵团制式战术裤",
      "foot": "A兵团制式战术皮鞋",
      "neck": "A兵团项链",
      "primary": "XM8",
      "secondary1": "韦森686",
      "secondary2": "韦森686",
      "melee": "斩马刀",
      "grenade": "普通手雷"
    }
  },
  {
    "level": 19,
    "name": "Lily",
    "id": 250,
    "height": 165,
    "face": 0,
    "hair": 22,
    "gender": "女",
    "equipment": {
      "head": "战术猪鼻式防毒面具",
      "body": "A兵团制式战术背心",
      "hand": "A兵团制式战术手套",
      "leg": "A兵团制式战术裤",
      "foot": "A兵团制式战术皮鞋",
      "neck": "A兵团项链",
      "primary": "XM8",
      "secondary1": "P90",
      "secondary2": "P90",
      "melee": "斩马刀",
      "grenade": "普通手雷"
    }
  },
  {
    "level": 22,
    "name": "陈骋",
    "id": 251,
    "height": 170,
    "face": 1,
    "hair": 35,
    "gender": "男",
    "equipment": {
      "head": "Andy装头",
      "body": "Andy上装",
      "hand": "Andy装手套",
      "leg": "Andy下装",
      "foot": "Andy装鞋",
      "neck": "Andy之心项圈",
      "primary": "M4A1改",
      "secondary1": "韦森686改装版",
      "secondary2": "韦森686改装版",
      "melee": "大剑",
      "grenade": "压缩胶囊之61套士兵"
    },
    "pricemultiplier": 1.5
  },
  {
    "level": 21,
    "name": "壮汉",
    "id": 23251,
    "height": 195,
    "face": 1,
    "hair": 35,
    "gender": "男",
    "equipment": {
      "head": "装甲头盔",
      "body": "军阀重装兵衣服",
      "hand": "军阀装甲手套",
      "leg": "军阀装甲裤",
      "foot": "军阀棕色皮靴",
      "neck": "战斗专家军牌",
      "primary": "M249",
      "secondary1": null,
      "secondary2": null,
      "melee": "斩马刀",
      "grenade": "压缩胶囊之61套士兵"
    }
  },
  {
    "level": 30,
    "name": "孤狼",
    "id": 252,
    "height": 175,
    "face": 1,
    "hair": 17,
    "gender": "男",
    "equipment": {
      "head": "精致战术猪鼻式防毒面具",
      "body": "A兵团精致战术背心",
      "hand": "A兵团精致战术手套",
      "leg": "A兵团精致战术裤",
      "foot": "A兵团精致战术皮鞋",
      "neck": "A兵团精致项链",
      "primary": "AK74",
      "secondary1": "Desert Eagle",
      "secondary2": "Desert Eagle",
      "melee": "光刀狮子",
      "grenade": null
    }
  },
  {
    "level": 35,
    "name": "铁甲",
    "id": 253,
    "height": 172,
    "face": 1,
    "hair": 17,
    "gender": "男",
    "equipment": {
      "head": "61式头部装甲",
      "body": "61式胸甲",
      "hand": "61式手甲",
      "leg": "61式腿甲",
      "foot": "61式装甲鞋",
      "neck": "战斗专家军牌",
      "primary": "M4A1战术版",
      "secondary1": "P90战术版",
      "secondary2": "P90战术版",
      "melee": "镜之虎彻",
      "grenade": null
    }
  },
  {
    "level": 40,
    "name": "影刃",
    "id": 254,
    "height": 170,
    "face": 1,
    "hair": 35,
    "gender": "男",
    "equipment": {
      "head": "幻影头部装甲",
      "body": "幻影胸甲",
      "hand": "幻影手甲",
      "leg": "幻影腿甲",
      "foot": "幻影装甲鞋",
      "neck": "战斗狂人军牌",
      "primary": "穿刺QBZ95",
      "secondary1": "穿刺LS06",
      "secondary2": "穿刺LS06",
      "melee": "烈焰斩马刀",
      "grenade": null
    }
  },
  {
    "level": 50,
    "name": "霸天虎",
    "id": 255,
    "height": 188,
    "face": 1,
    "hair": 41,
    "gender": "男",
    "equipment": {
      "head": "兽王虎甲盔",
      "body": "兽王虎甲",
      "hand": "兽王虎甲手套",
      "leg": "兽王虎甲腿甲",
      "foot": "兽王虎甲鞋",
      "neck": "屠戮者项链",
      "primary": null,
      "secondary1": null,
      "secondary2": null,
      "melee": null,
      "grenade": null
    },
    "pricemultiplier": 1.2
  },
  {
    "level": 70,
    "name": "卫天",
    "id": 256,
    "height": 191,
    "face": 1,
    "hair": 42,
    "gender": "男",
    "equipment": {
      "head": "兽王战甲盔",
      "body": "兽王战甲",
      "hand": "兽王战甲手套",
      "leg": "兽王战甲腿甲",
      "foot": "兽王战甲鞋",
      "neck": "金牌打手项链",
      "primary": null,
      "secondary1": null,
      "secondary2": null,
      "melee": null,
      "grenade": null
    }
  },
  {
    "level": 25,
    "name": "暴君之子",
    "id": 257,
    "height": 150,
    "face": 1,
    "hair": 39,
    "gender": "男",
    "equipment": {
      "head": "钢铁小熊头",
      "body": "钢铁小熊上装",
      "hand": "钢铁小熊手套",
      "leg": "钢铁小熊下装",
      "foot": "钢铁小熊鞋",
      "neck": "申猴项链",
      "primary": null,
      "secondary1": null,
      "secondary2": null,
      "melee": null,
      "grenade": null
    }
  },
  {
    "level": 17,
    "name": "武林宗师",
    "id": 2581,
    "height": 160,
    "face": 1,
    "hair": 39,
    "gender": "男",
    "equipment": {
      "head": null,
      "body": null,
      "hand": null,
      "leg": "白色功夫高手裤子",
      "foot": null,
      "neck": "金牌打手项链",
      "primary": "M3 Rocket Launcher",
      "secondary1": null,
      "secondary2": null,
      "melee": null,
      "grenade": null
    },
    "pricemultiplier": 0.9,
    "passive":{
      "轰炸专家":{"技能名":"轰炸专家", "等级":1, "启用":true}
    }
  },
  {
    "level": 20,
    "name": "王女",
    "id": 258,
    "height": 150,
    "face": 0,
    "hair": 23,
    "gender": "女",
    "equipment": {
      "head": "草莓味小熊头",
      "body": "草莓味小熊上装",
      "hand": "钢铁小熊手套",
      "leg": "草莓味小熊下装",
      "foot": "钢铁小熊鞋",
      "neck": "爱心勋章",
      "primary": null,
      "secondary1": null,
      "secondary2": null,
      "melee": null,
      "grenade": null
    }
  },
  {
    "level": 11,
    "name": "萝丝",
    "id": 259,
    "height": 160,
    "face": 0,
    "hair": 30,
    "gender": "女",
    "equipment": {
      "head": null,
      "body": "白色短袖校服",
      "hand": "小型拳套#3",
      "leg": "红色百褶短裙",
      "foot": "黑色白底皮鞋",
      "neck": "空手小加成项链",
      "primary": null,
      "secondary1": null,
      "secondary2": null,
      "melee": null,
      "grenade": null
    }
  },
  {
    "level": 5,
    "name": "地下拳王",
    "id": 260,
    "height": 170,
    "face": 1,
    "hair": 32,
    "gender": "男",
    "equipment": {
      "head": null,
      "body": null,
      "hand": "道钉手套",
      "leg": "金色腰带破洞牛仔裤",
      "foot": null,
      "neck": "爱国者军牌",
      "primary": null,
      "secondary1": null,
      "secondary2": null,
      "melee": null,
      "grenade": null
    }
  },
  {
    "level": 32,
    "name": "冷冰霜",
    "id": 261,
    "height": 170,
    "face": 1,
    "hair": 2,
    "gender": "男",
    "equipment": {
      "head": "次品蓝晶面具",
      "body": "次品蓝晶战斗服",
      "hand": "次品蓝晶手套",
      "leg": "次品蓝晶下装",
      "foot": "次品蓝晶鞋",
      "neck": "角斗高手项链",
      "primary": "巨兽",
      "secondary1": "P90战术版",
      "secondary2": "P90战术版",
      "melee": "冰魄斩",
      "grenade": null
    }
  },
  {
    "level": 36,
    "name": "寒冬",
    "id": 262,
    "height": 178,
    "face": 0,
    "hair": 23,
    "gender": "女",
    "equipment": {
      "head": "次品蓝晶面具",
      "body": "次品蓝晶战斗服",
      "hand": "次品蓝晶手套",
      "leg": "次品蓝晶下装",
      "foot": "次品蓝晶鞋",
      "neck": "角斗高手项链",
      "primary": "WA2000",
      "secondary1": "LS06",
      "secondary2": "LS06",
      "melee": "冰魄斩",
      "grenade": null
    }
  },
  {
    "level": 36,
    "name": "合金战士",
    "id": 263,
    "height": 182,
    "face": 1,
    "hair": 5,
    "gender": "男",
    "equipment": {
      "head": "合金盔",
      "body": "合金甲",
      "hand": "合金手套",
      "leg": "合金腿甲",
      "foot": "合金鞋",
      "neck": "角斗高手项链",
      "primary": "烈焰枪A100",
      "secondary1": "UZI战术版",
      "secondary2": "UZI战术版",
      "melee": "烈焰斩",
      "grenade": null
    },
    "pricemultiplier": 1.2
  },
  {
    "level": 39,
    "name": "炎",
    "id": 264,
    "height": 162,
    "face": 0,
    "hair": 21,
    "gender": "女",
    "equipment": {
      "head": "合金盔",
      "body": "合金甲",
      "hand": "合金手套",
      "leg": "合金腿甲",
      "foot": "合金鞋",
      "neck": "角斗王者项链",
      "primary": "烈焰枪B100",
      "secondary1": "极品UZI战术版",
      "secondary2": "极品UZI战术版",
      "melee": "烈焰斩",
      "grenade": null
    },
    "pricemultiplier": 1.2
  },
  {
    "level": 42,
    "name": "异形",
    "id": 265,
    "height": 200,
    "face": 1,
    "hair": 11,
    "gender": "男",
    "equipment": {
      "head": "异形骨盔",
      "body": "异形骨甲",
      "hand": "异形骨手套",
      "leg": "异形骨腿甲",
      "foot": "异形骨鞋",
      "neck": "角斗王者项链",
      "primary": "巴雷特",
      "secondary1": "战术版莫斯伯格590",
      "secondary2": "战术版莫斯伯格590",
      "melee": "异形毒刺",
      "grenade": null
    }
  },
  {
    "level": 45,
    "name": "舟歌",
    "id": 266,
    "height": 170,
    "face": 0,
    "hair": 22,
    "gender": "女",
    "equipment": {
      "head": "方舟武士盔",
      "body": "方舟武士甲",
      "hand": "方舟武士手套",
      "leg": "方舟武士腿甲",
      "foot": "方舟武士鞋",
      "neck": "角斗王者项链",
      "primary": "M202火箭发射器",
      "secondary1": "钛合金P90",
      "secondary2": "钛合金P90",
      "melee": "忍者佩剑",
      "grenade": null
    }
  },
  {
    "level": 50,
    "name": "忍者王",
    "id": 267,
    "height": 191,
    "face": 1,
    "hair": 4,
    "gender": "男",
    "equipment": {
      "head": "方舟武士盔",
      "body": "方舟武士甲",
      "hand": "方舟武士手套",
      "leg": "方舟武士腿甲",
      "foot": "方舟武士鞋",
      "neck": "角斗王者项链",
      "primary": "M134暴力版",
      "secondary1": "战术版MGL",
      "secondary2": "战术版MGL",
      "melee": "忍者佩剑",
      "grenade": null
    },
    "pricemultiplier": 1.3
  },
  {
    "level": 45,
    "name": "M055",
    "id": 5500,
    "height": 175,
    "face": 1,
    "hair": 8,
    "gender": "男",
    "equipment": {
      "head": "红外夜视仪##四阶",
      "body": "黑色重甲##三阶",
      "hand": "92式手甲",
      "leg": "新手裤子##四阶",
      "foot": "幻影装甲鞋",
      "neck": "余烬-“与光同尘”",
      "primary": "M4A1战术版",
      "secondary1": "战术版莫斯伯格590",
      "secondary2": "OPDW17",
      "melee": "激光剑",
      "grenade": null
    },
    "pricemultiplier": 1.5
  },
  {
    "level": 45,
    "name": "绯红佳人",
    "id": 5501,
    "height": 182,
    "face": 0,
    "hair": 50,
    "gender": "女",
    "equipment": {
      "head": "防毒面具1号##四阶",
      "body": "盗贼纹身装##三阶",
      "hand": "幻影手甲",
      "leg": "黑铁死士制式裤",
      "foot": "幻影装甲鞋",
      "neck": "余烬-“廉价筹码”",
      "primary": "白火铳",
      "secondary1": "韦森686改装版",
      "secondary2": "韦森686改装版",
      "melee": "巨尸长斧",
      "grenade": null
    },
    "pricemultiplier": 1.5
  },
  {
    "level": 41,
    "name": "枪匠",
    "id": 5502,
    "height": 168,
    "face": 1,
    "hair": 52,
    "gender": "男",
    "equipment": {
      "head": "黑色棒球帽##四阶",
      "body": "绿色马甲##四阶",
      "hand": "黑色皮手套##四阶",
      "leg": "新手裤子##四阶",
      "foot": "幻影装甲鞋",
      "neck": "余烬-“三位一体”",
      "primary": null,
      "secondary1": "战术版AK200",
      "secondary2": "战术版AK200",
      "melee": null,
      "grenade": null
    },
    "pricemultiplier": 1.5
  },
  {
    "level": 12,
    "name": "白夜",
    "id": 5503,
    "height": 150,
    "face": 0,
    "hair": 28,
    "gender": "女",
    "equipment": {
      "head": "科技潜入头盔",
      "body": "黑白女仆装##二阶",
      "hand": "科技潜入手套",
      "leg": "黑白女仆蕾丝短裙##二阶",
      "foot": "黑色白底皮鞋##二阶",
      "neck": "余烬-“白夜弥撒”",
      "primary": "G36",
      "secondary1": "Glock 18",
      "secondary2": "Glock 18",
      "melee": "虎彻",
      "grenade": null
    }
  },
  {
    "level": 41,
    "name": "剑痴",
    "id": 5504,
    "height": 180,
    "face": 1,
    "hair": 13,
    "gender": "男",
    "equipment": {
      "head": "剑圣头部装甲",
      "body": "剑圣胸甲",
      "hand": "剑圣手甲",
      "leg": "剑圣腿甲",
      "foot": "剑圣装甲鞋",
      "neck": "余烬-“如刃在喉”",
      "primary": null,
      "secondary1": null,
      "secondary2": null,
      "melee": "上古饮血大太刀",
      "grenade": null
    },
    "pricemultiplier": 1.5
  },
  {
    "level": 23,
    "name": "KEE-乐队主管",
    "id": 5505,
    "height": 165,
    "face": 0,
    "hair": 46,
    "gender": "女",
    "equipment": {
      "head": "棕色墨镜##二阶",
      "body": "A兵团精致战术背心",
      "hand": "Andy装手套",
      "leg": "黑丝灰色格子短裙",
      "foot": "BOSS2鞋子",
      "neck": "金牌打手项链",
      "primary": "吉他喷火器",
      "secondary1": null,
      "secondary2": null,
      "melee": "吉他喷火器",
      "grenade": null
    }
  },
  {
    "level": 19,
    "name": "Smart-吉他手",
    "id": 5506,
    "height": 178,
    "face": 1,
    "hair": 11,
    "gender": "男",
    "equipment": {
      "head": "杰森面具##二阶",
      "body": "bob自由牛仔衫##二阶",
      "hand": null,
      "leg": "bob自由喇叭裤##二阶",
      "foot": "bob自由火箭皮鞋##二阶",
      "neck": "金牌打手项链",
      "primary": "KRISS突击版",
      "secondary1": "KRISS",
      "secondary2": "KRISS",
      "melee": "桔色电子吉他",
      "grenade": null
    }
  },
  {
    "level": 20,
    "name": "Sundae-吉他手",
    "id": 5507,
    "height": 175,
    "face": 0,
    "hair": 29,
    "gender": "女",
    "equipment": {
      "head": "圣诞帽",
      "body": "黑灰色连帽马甲##二阶",
      "hand": "牛皮手套##二阶",
      "leg": "黑灰色毛边短裤##二阶",
      "foot": "黑灰色白底皮鞋##二阶",
      "neck": "金牌打手项链",
      "primary": null,
      "secondary1": null,
      "secondary2": "圣诞糖果枪",
      "melee": "红色电子吉他",
      "grenade": null
    }
  },
  {
    "level": 18,
    "name": "Coco-电子琴",
    "id": 5508,
    "height": 156,
    "face": 0,
    "hair": 53,
    "gender": "女",
    "equipment": {
      "head": "黑框眼镜##二阶",
      "body": "白色短袖校服##二阶",
      "hand": null,
      "leg": "红色百褶短裙##二阶",
      "foot": "白色袜子",
      "neck": "金牌打手项链",
      "primary": null,
      "secondary1": null,
      "secondary2": "UZI",
      "melee": "电子音乐键盘",
      "grenade": null
    }
  },
  {
    "level": 20,
    "name": "BErminAtoR-贝斯手",
    "id": 5509,
    "height": 150,
    "face": 1,
    "hair": 51,
    "gender": "男",
    "equipment": {
      "head": "双色巧克力味小熊头",
      "body": "钢铁小熊上装",
      "hand": "钢铁小熊手套",
      "leg": "双色巧克力味小熊下装",
      "foot": "钢铁小熊鞋",
      "neck": "金牌打手项链",
      "primary": null,
      "secondary1": null,
      "secondary2": null,
      "melee": null,
      "grenade": null
    }
  },
  {
    "level": 1,
    "name": "管家",
    "id": 5510,
    "height": 175,
    "face": 1,
    "hair": 33,
    "gender": "男",
    "equipment": {
      "head": "黑框眼镜",
      "body": "黑色西装",
      "hand": "黑色皮手套",
      "leg": "黑色西装裤",
      "foot": "黑色军用皮鞋",
      "neck": "爱心勋章",
      "primary": null,
      "secondary1": "PPK",
      "secondary2": null,
      "melee": null,
      "grenade": null
    },
    "pricemultiplier": 1.2
  },
  {
    "level": 12,
    "name": "刘沛松",
    "id": 5511,
    "height": 180,
    "face": 1,
    "hair": 7,
    "gender": "男",
    "equipment": {
      "head": "黑色摩托头盔##二阶",
      "body": "褐色皮衣##二阶",
      "hand": "道钉手套##二阶",
      "leg": "盗贼褐色皮裤##二阶",
      "foot": "褐色厚底皮鞋##二阶",
      "neck": "新手军牌",
      "primary": null,
      "secondary1": null,
      "secondary2": null,
      "melee": "美式警棍",
      "grenade": null
    }
  },
  {
    "level": 12,
    "name": "荘臣",
    "id": 5512,
    "height": 185,
    "face": 1,
    "hair": 7,
    "gender": "男",
    "equipment": {
      "head": "黑色摩托头盔##二阶",
      "body": "橘色赛车夹克##二阶",
      "hand": "黑色皮手套##二阶",
      "leg": "墨绿军用下装##二阶",
      "foot": "墨绿军用鞋##二阶",
      "neck": "新手军牌",
      "primary": null,
      "secondary1": null,
      "secondary2": null,
      "melee": "棒球棒",
      "grenade": null
    }
  },
  {
    "level": 7,
    "name": "阿龙",
    "id": 5513,
    "height": 172,
    "face": 1,
    "hair": 41,
    "gender": "男",
    "equipment": {
      "head": "红色风镜",
      "body": "褐色皮带装",
      "hand": "红色皮手套",
      "leg": "破牛仔裤",
      "foot": "棕色皮鞋",
      "neck": null,
      "primary": "AK47",
      "secondary1": null,
      "secondary2": null,
      "melee": "水管",
      "grenade": null
    }
  },
  {
    "level": 6,
    "name": "左疼君",
    "id": 5514,
    "height": 175,
    "face": 1,
    "hair": 5,
    "gender": "男",
    "equipment": {
      "head": null,
      "body": "休闲马甲",
      "hand": null,
      "leg": "咖啡色多包短裤",
      "foot": "白色板鞋",
      "neck": null,
      "primary": null,
      "secondary1": "M1911",
      "secondary2": null,
      "melee": "棒球棒",
      "grenade": null
    }
  },
  {
    "level": 8,
    "name": "智芝辛",
    "id": 5515,
    "height": 175,
    "face": 1,
    "hair": 16,
    "gender": "男",
    "equipment": {
      "head": null,
      "body": "蓝色西式校服",
      "hand": "白色手套",
      "leg": "蓝色条纹裤子",
      "foot": "蓝白相间校鞋",
      "neck": null,
      "primary": "AK47",
      "secondary1": null,
      "secondary2": null,
      "melee": null,
      "grenade": null
    }
  },
  {
    "level": 6,
    "name": "尚誉",
    "id": 5516,
    "height": 174,
    "face": 1,
    "hair": 15,
    "gender": "男",
    "equipment": {
      "head": "黑框眼镜",
      "body": "黑色立领校服",
      "hand": "白色手套",
      "leg": "黑色校服裤子",
      "foot": "黑色条纹运动鞋",
      "neck": null,
      "primary": null,
      "secondary1": "Glock 18",
      "secondary2": null,
      "melee": "短棒",
      "grenade": null
    }
  },
  {
    "level": 10,
    "name": "喜欢医闹？",
    "id": 5517,
    "height": 175,
    "face": 0,
    "hair": 40,
    "gender": "女",
    "equipment": {
      "head": "医用口罩",
      "body": "白色短袖校服",
      "hand": "白色手套",
      "leg": "黑白女仆蕾丝短裙",
      "foot": "科技潜入靴",
      "neck": "爱心勋章",
      "primary": null,
      "secondary1": null,
      "secondary2": null,
      "melee": "双面斧",
      "grenade": null
    }
  },
  {
    "level": 65,
    "name": "临界点",
    "id": 5518,
    "height": 182,
    "face": 1,
    "hair": 34,
    "gender": "男",
    "equipment": {
      "head": "远古忍者盔",
      "body": "诛神胸甲",
      "hand": "蓝晶手套",
      "leg": "蓝晶下装",
      "foot": "蓝晶鞋",
      "neck": "诛神项链",
      "primary": "量子能量枪",
      "secondary1": null,
      "secondary2": null,
      "melee": "冰魄神斩",
      "grenade": null
    }
  },
  {
    "level": 68,
    "name": "卡塔利纳的杰克巴尔",
    "id": 5519,
    "height": 175,
    "face": 1,
    "hair": 34,
    "gender": "男",
    "equipment": {
      "head": "诛神头盔",
      "body": "诛神胸甲",
      "hand": "诛神手套",
      "leg": "诛神腿甲",
      "foot": "诛神战鞋",
      "neck": "诛神项链",
      "primary": "诛神枪",
      "secondary1": "诛神短枪",
      "secondary2": "诛神短枪",
      "melee": "诛神剑",
      "grenade": null
    }
  },
  {
    "level": 30,
    "name": "C国队长",
    "id": 5520,
    "height": 178,
    "face": 1,
    "hair": 6,
    "gender": "男",
    "equipment": {
      "head": "黑色太阳镜##三阶",
      "body": "沙漠军装背心##三阶",
      "hand": "道钉手套##三阶",
      "leg": "沙漠军装裤##三阶",
      "foot": "沙漠军装皮鞋##三阶",
      "neck": "爱国者军牌",
      "primary": "中国88式狙击步枪改造版",
      "secondary1": "中国54式手枪",
      "secondary2": "中国54式手枪",
      "melee": "爪刀",
      "grenade": null
    },
    "pricemultiplier": 0.8
  },
  {
    "level": 15,
    "name": "陈真",
    "id": 5521,
    "height": 175,
    "face": 1,
    "hair": 35,
    "gender": "男",
    "equipment": {
      "head": null,
      "body": "白色中山上装##二阶",
      "hand": "白色手套##二阶",
      "leg": "白色中山装裤子##二阶",
      "foot": "褐色简单皮鞋##二阶",
      "neck": "轶事奇人",
      "primary": null,
      "secondary1": "毛瑟手枪",
      "secondary2": "毛瑟手枪",
      "melee": "中国战刀",
      "grenade": null
    }
  },
  {
    "level": 15,
    "name": "春笠",
    "id": 5522,
    "height": 165,
    "face": 0,
    "hair": 24,
    "gender": "女",
    "equipment": {
      "head": null,
      "body": "红黑色功夫装##二阶",
      "hand": "福袋",
      "leg": "黑色功夫短裤##二阶",
      "foot": "红色功夫布鞋##二阶",
      "neck": "轶事奇人",
      "primary": null,
      "secondary1": null,
      "secondary2": null,
      "melee": "狸灰直刃",
      "grenade": null
    }
  },
  {
    "level": 15,
    "name": "学生姐",
    "id": 5523,
    "height": 180,
    "face": 0,
    "hair": 22,
    "gender": "女",
    "equipment": {
      "head": null,
      "body": "黑色长袖学生制服##二阶",
      "hand": null,
      "leg": "红色格子短裙##二阶",
      "foot": "咖啡色学生皮鞋##二阶",
      "neck": "轶事奇人",
      "primary": null,
      "secondary1": "MK23手枪",
      "secondary2": "MK23手枪",
      "melee": "虎彻",
      "grenade": null
    }
  },
  {
    "level": 14,
    "name": "首相の最强保镖",
    "id": 5524,
    "height": 165,
    "face": 0,
    "hair": 42,
    "gender": "女",
    "equipment": {
      "head": "红外线滤光镜",
      "body": "黑灰色深V紧身衣",
      "hand": "白色手套",
      "leg": "黑色西装裤",
      "foot": "黑色高跟皮鞋",
      "neck": "守护者军牌",
      "primary": null,
      "secondary1": "Glock 18",
      "secondary2": "Glock 18",
      "melee": null,
      "grenade": null
    }
  },
  {
    "level": 21,
    "name": "猎狐者",
    "id": 5525,
    "height": 165,
    "face": 0,
    "hair": 13,
    "gender": "女",
    "equipment": {
      "head": "圆框墨镜",
      "body": "绿色马甲##二阶",
      "hand": "棕色手套",
      "leg": "黑色功夫短裤",
      "foot": "深灰色皮鞋",
      "neck": "调停者军牌",
      "primary": "Sniper",
      "secondary1": null,
      "secondary2": "Glock 18",
      "melee": "单刀",
      "grenade": null
    }
  },
  {
    "level": 50,
    "name": "魅影",
    "id": 5526,
    "height": 168,
    "face": 0,
    "hair": 28,
    "gender": "女",
    "equipment": {
      "head": "方舟武士盔",
      "body": "黑铁死士绑带",
      "hand": null,
      "leg": "SM女王吊带袜",
      "foot": null,
      "neck": "屠戮者项链",
      "primary": "追月弩",
      "secondary1": null,
      "secondary2": null,
      "melee": null,
      "grenade": null
    },
    "pricemultiplier": 0.6
  },
  {
    "level": 31,
    "name": "彗星",
    "id": 5528,
    "height": 165,
    "face": 0,
    "hair": 26,
    "gender": "女",
    "equipment": {
      "head": "锐刻幻影夜视仪",
      "body": "keyboard衣服",
      "hand": "黑色皮手套##三阶",
      "leg": "次品蓝晶下装",
      "foot": "幻影装甲鞋",
      "neck": "余烬队徽",
      "primary": "中国88式狙击步枪改造版",
      "secondary1": "KRISS轻量化突击版",
      "secondary2": "KRISS轻量化突击版",
      "melee": "光刃摩羯",
      "grenade": null
    }
  },
  {
    "level": 64,
    "name": "XV秩律-执裁者",
    "id": 5528,
    "height": 185,
    "face": 0,
    "hair": 26,
    "gender": "女",
    "equipment": {
      "head": "炎魔盔",
      "body": "61式胸甲",
      "hand": "61式手甲",
      "leg": "炎魔腿甲",
      "foot": "炎魔鞋",
      "neck": "战斗专家军牌",
      "primary": "战术版喷火器",
      "secondary1": null,
      "secondary2": null,
      "melee": "血色光剑天秤",
      "grenade": null
    }
  },
  {
    "level": 62,
    "name": "XV秩律-断罪者",
    "id": 5529,
    "height": 180,
    "face": 0,
    "hair": 22,
    "gender": "女",
    "equipment": {
      "head": "蓝晶面具",
      "body": "方舟武士甲",
      "hand": "蓝晶手套",
      "leg": "蓝晶下装",
      "foot": "方舟武士鞋",
      "neck": "战斗专家军牌",
      "primary": null,
      "secondary1": "轻量化量子能量枪",
      "secondary2": null,
      "melee": "绝地武士佩剑",
      "grenade": null
    }
  },
  {
    "level": 60,
    "name": "XV秩律-判罚者",
    "id": 5530,
    "height": 190,
    "face": 1,
    "hair": 44,
    "gender": "男",
    "equipment": {
      "head": "精致战术猪鼻式防毒面具",
      "body": "钛合金61式胸甲",
      "hand": "钛合金61式手甲",
      "leg": "炎魔腿甲",
      "foot": "61式装甲鞋",
      "neck": "战斗专家军牌",
      "primary": "战术版FIM92",
      "secondary1": "战术版MGL",
      "secondary2": "战术版MGL",
      "melee": "雷神之锤",
      "grenade": null
    }
  },
  {
    "level": 35,
    "name": "黑蜂",
    "id": 5531,
    "height": 160,
    "face": 0,
    "hair": 13,
    "gender": "女",
    "equipment": {
      "head": "复镕望远热感仪",
      "body": "新手衣服##四阶",
      "hand": "61式手甲",
      "leg": "幻影腿甲",
      "foot": "新手皮鞋##四阶",
      "neck": "余烬队徽",
      "primary": "M202火箭发射器",
      "secondary1": null,
      "secondary2": null,
      "melee": null,
      "grenade": null
    }
  },
  {
    "level": 40,
    "name": "我要打一百个",
    "id": 5532,
    "height": 180,
    "face": 1,
    "hair": 44,
    "gender": "男",
    "equipment": {
      "head": "天山黑侠帽子#10",
      "body": "天山黑侠上装#10",
      "hand": "兽王虎甲手套#13",
      "leg": "天山黑侠裤子#10",
      "foot": "天山黑侠棕色皮鞋#10",
      "neck": "战斗专家军牌#10",
      "primary": null,
      "secondary1": null,
      "secondary2": null,
      "melee": null,
      "grenade": null
    },
    "pricemultiplier": 0.9
  },
  {
    "level": 13,
    "name": "斑纹",
    "id": 5533,
    "height": 175,
    "face": 1,
    "hair": 43,
    "gender": "男",
    "equipment": {
      "head": "咖啡色条纹蒙面",
      "body": "褐色背带背心",
      "hand": "红色皮手套",
      "leg": "军阀普通带腿包军裤",
      "foot": "沙漠军装皮鞋",
      "neck": "新手军牌",
      "primary": "AK47",
      "secondary1": null,
      "secondary2": null,
      "melee": "消防斧",
      "grenade": null
    }
  },
  {
    "level": 20,
    "name": "小樱",
    "id": 5534,
    "height": 156,
    "face": 0,
    "hair": 28,
    "gender": "女",
    "equipment": {
      "head": "棕色墨镜##二阶",
      "body": "沙漠军装背心",
      "hand": "牛皮手套##二阶",
      "leg": "棕色带腿包短裤##二阶",
      "foot": "军阀棕色皮靴",
      "neck": "僵尸克星军牌",
      "primary": "AUG",
      "secondary1": "Desert Eagle",
      "secondary2": null,
      "melee": "唐朝七星剑",
      "grenade": null
    }
  },
  {
    "level": 21,
    "name": "安德森",
    "id": 5535,
    "height": 182,
    "face": 1,
    "hair": 35,
    "gender": "男",
    "equipment": {
      "head": "沙漠军装头盔##二阶",
      "body": "军阀突击兵衣服",
      "hand": "牛皮手套##二阶",
      "leg": "沙漠军装裤",
      "foot": "沙漠军装皮鞋",
      "neck": "僵尸克星军牌",
      "primary": "AK74",
      "secondary1": "Desert Eagle",
      "secondary2": null,
      "melee": "stridermantrack匕首",
      "grenade": null
    }
  },
  {
    "level": 65,
    "name": "亚德南丘",
    "id": 5536,
    "height": 160,
    "face": 0,
    "hair": 22,
    "gender": "女",
    "equipment": {
      "head": "科技潜入头盔",
      "body": "远古忍者甲",
      "hand": "远古忍者手套",
      "leg": "科技潜入裤子",
      "foot": "科技潜入靴",
      "neck": "接触者军牌",
      "primary": "诺亚方舟护士狙击步枪",
      "secondary1": "改造式诺亚科技冲锋枪",
      "secondary2": "改造式诺亚科技冲锋枪",
      "melee": "绝地武士佩剑",
      "grenade": null
    }
  },
  {
    "level": 70,
    "name": "普罗米修斯",
    "id": 5537,
    "height": 188,
    "face": 1,
    "hair": 34,
    "gender": "男",
    "equipment": {
      "head": "远古忍者盔",
      "body": "远古忍者甲",
      "hand": "远古忍者手套",
      "leg": "远古忍者腿甲",
      "foot": "远古忍者鞋",
      "neck": "接触者军牌",
      "primary": "诺亚卫士科技步枪",
      "secondary1": "轻量化量子能量枪",
      "secondary2": "轻量化量子能量枪",
      "melee": "血色光剑天秤",
      "grenade": null
    }
  },
  {
    "level": 28,
    "name": "鹰眼",
    "id": 5538,
    "height": 179,
    "face": 1,
    "hair": 18,
    "gender": "男",
    "equipment": {
      "head": "锐刻幻影夜视仪",
      "body": "沙漠军装背心",
      "hand": "Andy装手套",
      "leg": "军阀带腰包裤子",
      "foot": "沙漠军装皮鞋",
      "neck": "金牌打手项链",
      "primary": "芬兰之星",
      "secondary1": "韦森686",
      "secondary2": null,
      "melee": "maddog疯狗刀",
      "grenade": null
    }
  },
  {
    "level": 26,
    "name": "战车",
    "id": 5539,
    "height": 180,
    "face": 1,
    "hair": 43,
    "gender": "男",
    "equipment": {
      "head": "圆框墨镜##三阶",
      "body": "军绿防弹衣##三阶",
      "hand": null,
      "leg": "军阀装甲裤",
      "foot": "军阀棕色皮靴",
      "neck": "生存者军牌",
      "primary": "PKM机枪",
      "secondary1": "P90战术版",
      "secondary2": "P90战术版",
      "melee": "方钢锤",
      "grenade": null
    }
  },
  {
    "level": 45,
    "name": "威克钛手",
    "id": 5540,
    "height": 180,
    "face": 1,
    "hair": 2,
    "gender": "男",
    "equipment": {
      "head": "次品蓝晶面具#6",
      "body": "蓝晶战斗服#6",
      "hand": "钛合金61式手甲#10",
      "leg": "次品蓝晶下装#6",
      "foot": "幻影装甲鞋#6",
      "neck": "战斗狂人军牌#6",
      "primary": "极品巨兽#6",
      "secondary1": "牛仔的左轮#6",
      "secondary2": "牛仔的左轮#6",
      "melee": "镜之虎彻#6",
      "grenade": null
    }
  },
  {
    "level": 35,
    "name": "Locke-Lee",
    "id": 5541,
    "height": 160,
    "face": 1,
    "hair": 4,
    "gender": "男",
    "equipment": {
      "head": "幻影头部装甲",
      "body": "幻影胸甲",
      "hand": "61式手甲",
      "leg": "合金腿甲",
      "foot": "幻影装甲鞋",
      "neck": "生存者军牌",
      "primary": "AWP",
      "secondary1": null,
      "secondary2": null,
      "melee": "烈焰斩马刀",
      "grenade": null
    }
  },
  {
    "level": 40,
    "name": "虎威太岁",
    "id": 5542,
    "height": 200,
    "face": 1,
    "hair": 34,
    "gender": "男",
    "equipment": {
      "head": "兽王虎甲盔",
      "body": "军阀重装兵衣服",
      "hand": "A兵团制式战术手套",
      "leg": "92式腿甲",
      "foot": "墨绿军用鞋##四阶",
      "neck": "战斗狂人军牌",
      "primary": "M202火箭发射器",
      "secondary1": null,
      "secondary2": null,
      "melee": null,
      "grenade": null
    }
  },
  {
    "level": 47,
    "name": "天启",
    "id": 5543,
    "height": 182,
    "face": 1,
    "hair": 44,
    "gender": "男",
    "equipment": {
      "head": "精致战术猪鼻式防毒面具",
      "body": "A兵团精致战术背心",
      "hand": "A兵团精致战术手套",
      "leg": "92式腿甲",
      "foot": "92式装甲鞋",
      "neck": "接触者军牌",
      "primary": "AK74战术版",
      "secondary1": "战术版莫斯伯格590",
      "secondary2": "战术版莫斯伯格590",
      "melee": "十文字大剑",
      "grenade": null
    },
    "pricemultiplier": 0.8
  },
  {
    "level": 45,
    "name": "九尾狐",
    "id": 5544,
    "height": 160,
    "face": 0,
    "hair": 28,
    "gender": "女",
    "equipment": {
      "head": "精致战术猪鼻式防毒面具",
      "body": "A兵团精致战术背心",
      "hand": "钛合金61式手甲",
      "leg": "蓝晶下装",
      "foot": "幻影装甲鞋",
      "neck": "接触者军牌",
      "primary": "M4A1战术版",
      "secondary1": "穿刺LS06",
      "secondary2": "穿刺LS06",
      "melee": "镜之虎彻",
      "grenade": null
    }
  },
  {
    "level": 13,
    "name": "利剑",
    "id": 5545,
    "height": 180,
    "face": 1,
    "hair": 2,
    "gender": "男",
    "equipment": {
      "head": "防毒面具2号##二阶",
      "body": "A兵团制式战术背心",
      "hand": "A兵团制式战术手套",
      "leg": "新手裤子##二阶",
      "foot": "新手皮鞋##二阶",
      "neck": "调停者军牌",
      "primary": "G36",
      "secondary1": "TMP",
      "secondary2": "TMP",
      "melee": "大剑",
      "grenade": null
    }
  },
  {
    "level": 15,
    "name": "卫队长",
    "id": 5546,
    "height": 182,
    "face": 1,
    "hair": 12,
    "gender": "男",
    "equipment": {
      "head": "A兵团三相猪鼻式防毒面具",
      "body": "警用防爆服背心##二阶",
      "hand": "A兵团制式战术手套",
      "leg": "新手裤子##二阶",
      "foot": "黑色军用皮鞋##二阶",
      "neck": "调停者军牌",
      "primary": "汤姆逊冲锋枪",
      "secondary1": "Mp5 pdw",
      "secondary2": "Mp5 pdw",
      "melee": "stridermantrack匕首",
      "grenade": null
    }
  },
  {
    "level": 14,
    "name": "朱古力",
    "id": 5547,
    "height": 156,
    "face": 0,
    "hair": 13,
    "gender": "女",
    "equipment": {
      "head": "黑铁死士围巾",
      "body": "新手衣服##二阶",
      "hand": "牛皮手套##二阶",
      "leg": "黑铁死士制式裤",
      "foot": "新手皮鞋##二阶",
      "neck": "调停者军牌",
      "primary": "M4A1",
      "secondary1": "Glock 18",
      "secondary2": "Glock 18",
      "melee": "快开小折刀",
      "grenade": null
    }
  },
  {
    "level": 15,
    "name": "沉淀哥",
    "id": 5548,
    "height": 187,
    "face": 1,
    "hair": 4,
    "gender": "男",
    "equipment": {
      "head": "新手面具##二阶",
      "body": "黑短袖##二阶",
      "hand": null,
      "leg": "新手裤子##二阶",
      "foot": "新手皮鞋##二阶",
      "neck": "调停者军牌",
      "primary": "M249",
      "secondary1": null,
      "secondary2": null,
      "melee": "单刃斧头",
      "grenade": null
    }
  },
  {
    "level": 20,
    "name": "腕豪",
    "id": 5549,
    "height": 182,
    "face": 1,
    "hair": 9,
    "gender": "男",
    "equipment": {
      "head": "仿制A兵团战术猪鼻式防毒面具",
      "body": "黑色功夫装##二阶",
      "hand": "钢铁小熊手套",
      "leg": "警用防爆服裤##二阶",
      "foot": "天山黑侠棕色皮鞋",
      "neck": "调停者军牌",
      "primary": null,
      "secondary1": null,
      "secondary2": null,
      "melee": null,
      "grenade": null
    }
  },
  {
    "level": 17,
    "name": "探戈狼",
    "id": 5550,
    "height": 178,
    "face": 0,
    "hair": 48,
    "gender": "女",
    "equipment": {
      "head": "黑铁死士围巾",
      "body": "黑铁死士绑带",
      "hand": "牛皮手套##二阶",
      "leg": "A兵团制式战术裤",
      "foot": "黑铁死士鞋",
      "neck": "屠戮者项链",
      "primary": "XM8",
      "secondary1": "Mossberg500",
      "secondary2": "Mossberg500",
      "melee": "唐朝直刀",
      "grenade": null
    }
  },
  {
    "level": 18,
    "name": "刹",
    "id": 5551,
    "height": 150,
    "face": 0,
    "hair": 25,
    "gender": "女",
    "equipment": {
      "head": "黑铁死士围巾",
      "body": "SM女王皮衣##二阶",
      "hand": "黑铁死士手套",
      "leg": "黑铁死士制式裤",
      "foot": "黑铁死士鞋",
      "neck": "生存者军牌",
      "primary": "UMP",
      "secondary1": "韦森686",
      "secondary2": "COLT PYTHON",
      "melee": "忍者佩剑",
      "grenade": null
    }
  },
  {
    "level": 27,
    "name": "万宝路",
    "id": 5552,
    "height": 179,
    "face": 1,
    "hair": 54,
    "gender": "男",
    "equipment": {
      "head": "A兵团独眼龙防毒面具",
      "body": "A兵团精致战术背心",
      "hand": "A兵团精致战术手套",
      "leg": "A兵团精致战术裤",
      "foot": "A兵团精致战术皮鞋",
      "neck": "地球卫士项链",
      "primary": "雷明登870",
      "secondary1": "P90",
      "secondary2": "P90",
      "melee": "消防斧",
      "grenade": null
    }
  },
  {
    "level": 24,
    "name": "飓风",
    "id": 5553,
    "height": 189,
    "face": 0,
    "hair": 23,
    "gender": "女",
    "equipment": {
      "head": "A兵团半遮脸猪鼻式防毒面具",
      "body": "黑铁行刑者绑带",
      "hand": "A兵团制式战术手套",
      "leg": "A兵团制式战术裤",
      "foot": "黑铁行刑者鞋",
      "neck": "A兵团项链",
      "primary": "MG42",
      "secondary1": "Desert Eagle",
      "secondary2": "牛仔的左轮",
      "melee": "西洋重剑",
      "grenade": null
    }
  },
  {
    "level": 25,
    "name": "佚龙",
    "id": 5554,
    "height": 183,
    "face": 0,
    "hair": 13,
    "gender": "女",
    "equipment": {
      "head": "红外夜视仪##三阶",
      "body": "A兵团精致战术背心",
      "hand": "黑铁行刑者手套",
      "leg": "黑铁行刑者制式裤",
      "foot": "黑铁行刑者鞋",
      "neck": "A兵团精致项链",
      "primary": "m14",
      "secondary1": "KRISS轻量化突击版",
      "secondary2": "KRISS轻量化突击版",
      "melee": "上古青萍元气剑",
      "grenade": null
    }
  },
  {
    "level": 30,
    "name": "赤丸",
    "id": 5555,
    "height": 190,
    "face": 0,
    "hair": 47,
    "gender": "女",
    "equipment": {
      "head": "般若赤鬼半覆面",
      "body": "剑圣胸甲",
      "hand": "剑圣手甲",
      "leg": "A兵团精致战术裤",
      "foot": "剑圣装甲鞋",
      "neck": "战斗专家军牌",
      "primary": "白火铳",
      "secondary1": "UZI战术版",
      "secondary2": "UZI战术版",
      "melee": "苍面银牙",
      "grenade": null
    }
  },
  {
    "level": 36,
    "name": "嘚吧呦",
    "id": 5556,
    "height": 160,
    "face": 1,
    "hair": 19,
    "gender": "男",
    "equipment": {
      "head": "次品蓝晶面具",
      "body": "Andy上装",
      "hand": "Andy装手套",
      "leg": "A兵团制式战术裤",
      "foot": "A兵团精致战术皮鞋",
      "neck": "战斗专家军牌",
      "primary": "WA2000",
      "secondary1": "MP5战术版",
      "secondary2": "MP5战术版",
      "melee": "秋月",
      "grenade": null
    }
  },
  {
    "level": 30,
    "name": "压制者",
    "id": 5557,
    "height": 200,
    "face": 0,
    "hair": 52,
    "gender": "女",
    "equipment": {
      "head": "警用防爆服头盔##三阶",
      "body": "92式胸甲",
      "hand": "A兵团精致战术手套",
      "leg": "A兵团制式战术裤",
      "foot": "墨绿军用鞋##三阶",
      "neck": "守护者军牌",
      "primary": "XM1014战术版",
      "secondary1": null,
      "secondary2": null,
      "melee": "电感切割刃",
      "grenade": null
    }
  },
  {
    "level": 12,
    "name": "红衫",
    "id": 5558,
    "height": 170,
    "face": 1,
    "hair": 6,
    "gender": "男",
    "equipment": {
      "head": "红色风镜",
      "body": "红黑色功夫装##二阶",
      "hand": "红色皮手套",
      "leg": "沙漠军装裤",
      "foot": "沙漠军装皮鞋",
      "neck": "新手军牌",
      "primary": "53式步骑枪",
      "secondary1": null,
      "secondary2": null,
      "melee": "破旧的军刀",
      "grenade": null
    }
  },
  {
    "level": 36,
    "name": "雷云",
    "id": 5559,
    "height": 177,
    "face": 0,
    "hair": 43,
    "gender": "女",
    "equipment": {
      "head": "防毒面具1号##四阶",
      "body": "A兵团精致战术背心",
      "hand": "牛皮手套##四阶",
      "leg": "Andy下装",
      "foot": "沙漠军装皮鞋##四阶",
      "neck": "战斗专家军牌",
      "primary": "芬兰之星",
      "secondary1": "韦森686改装版",
      "secondary2": null,
      "melee": "黑铁巨斧",
      "grenade": null
    }
  },
  {
    "level": 37,
    "name": "执行者",
    "id": 5560,
    "height": 165,
    "face": 0,
    "hair": 31,
    "gender": "女",
    "equipment": {
      "head": "防毒面具2号##四阶",
      "body": "A兵团精致战术背心",
      "hand": "黑色皮手套##四阶",
      "leg": "警用防爆服裤##四阶",
      "foot": "黑色军用皮鞋##四阶",
      "neck": "调停者军牌",
      "primary": "牛仔的温切斯特",
      "secondary1": null,
      "secondary2": null,
      "melee": "战术黑刀",
      "grenade": null
    }
  },
  {
    "level": 36,
    "name": "白幽灵",
    "id": 5561,
    "height": 170,
    "face": 0,
    "hair": 3,
    "gender": "女",
    "equipment": {
      "head": "次品蓝晶面具",
      "body": "科技潜入上装",
      "hand": "A兵团精致战术手套",
      "leg": "次品蓝晶下装",
      "foot": "次品蓝晶鞋",
      "neck": "战斗专家军牌",
      "primary": "AWP",
      "secondary1": "恒宇银星",
      "secondary2": "恒宇银星",
      "melee": "冰魄斩",
      "grenade": null
    }
  },
  {
    "level": 25,
    "name": "诸葛叁",
    "id": 5562,
    "height": 170,
    "face": 1,
    "hair": 13,
    "gender": "男",
    "equipment": {
      "head": "黑色棒球帽##三阶",
      "body": "Andy上装",
      "hand": "A兵团精致战术手套",
      "leg": "墨绿军用下装##四阶",
      "foot": "A兵团精致战术皮鞋",
      "neck": "未羊项链",
      "primary": "AK200",
      "secondary1": "加强版mp7",
      "secondary2": "加强版mp7",
      "melee": "光刃摩羯",
      "grenade": null
    }
  },
  {
    "level": 33,
    "name": "门神",
    "id": 5563,
    "height": 187,
    "face": 1,
    "hair": 35,
    "gender": "男",
    "equipment": {
      "head": "般若影鬼半覆面",
      "body": "A兵团精致战术背心",
      "hand": "61式手甲",
      "leg": "剑圣腿甲",
      "foot": "剑圣装甲鞋",
      "neck": "申猴项链",
      "primary": "XM1014战术版",
      "secondary1": "恒宇红星",
      "secondary2": "恒宇红星",
      "melee": "长墨白铁",
      "grenade": null
    }
  },
  {
    "level": 40,
    "name": "红桃K",
    "id": 5564,
    "height": 189,
    "face": 1,
    "hair": 48,
    "gender": "男",
    "equipment": {
      "head": "杰森面具##四阶",
      "body": "剑圣胸甲",
      "hand": "弗莱迪手套##四阶",
      "leg": "墨绿军用下装##四阶",
      "foot": "剑圣装甲鞋",
      "neck": "战斗狂人军牌",
      "primary": "中国湖榴弹发射器",
      "secondary1": null,
      "secondary2": null,
      "melee": "忍者执剑",
      "grenade": null
    }
  },
  {
    "level": 22,
    "name": "大表哥",
    "id": 5565,
    "height": 182,
    "face": 1,
    "hair": 15,
    "gender": "男",
    "equipment": {
      "head": "战术耳机加遮阳帽",
      "body": "绿色马甲##二阶",
      "hand": "黑色皮手套##二阶",
      "leg": "战术套装裤子",
      "foot": "新手皮鞋##二阶",
      "neck": "僵尸割草机军牌",
      "primary": "FNSLP半自动霰弹枪",
      "secondary1": null,
      "secondary2": null,
      "melee": "棒球棒",
      "grenade": null
    }
  },
  {
    "level": 21,
    "name": "老藏",
    "id": 5566,
    "height": 173,
    "face": 1,
    "hair": 43,
    "gender": "男",
    "equipment": {
      "head": "黑色太阳镜##二阶",
      "body": "军阀弹药兵衣服##二阶",
      "hand": "牛皮手套##二阶",
      "leg": "军阀普通带腿包军裤##二阶",
      "foot": "新手皮鞋##二阶",
      "neck": "僵尸割草机军牌",
      "primary": "Sniper",
      "secondary1": null,
      "secondary2": null,
      "melee": "匕首",
      "grenade": null
    }
  },
  {
    "level": 20,
    "name": "文杰他弟",
    "id": 5567,
    "height": 178,
    "face": 1,
    "hair": 44,
    "gender": "男",
    "equipment": {
      "head": null,
      "body": "战术套装上衣",
      "hand": "牛皮手套##二阶",
      "leg": "新手裤子##二阶",
      "foot": "新手皮鞋##二阶",
      "neck": "僵尸克星军牌",
      "primary": "AK200",
      "secondary1": "Desert Eagle",
      "secondary2": "Desert Eagle",
      "melee": "斩马刀",
      "grenade": null
    }
  },
  {
    "level": 55,
    "name": "日冕",
    "id": 5568,
    "height": 185,
    "face": 1,
    "hair": 7,
    "gender": "男",
    "equipment": {
      "head": "蓝晶面具",
      "body": "钛合金61式胸甲",
      "hand": "炎魔手套",
      "leg": "炎魔腿甲",
      "foot": "剑圣装甲鞋",
      "neck": "战斗专家军牌",
      "primary": "炎魔枪B100",
      "secondary1": null,
      "secondary2": null,
      "melee": "炎魔斩new",
      "grenade": null
    }
  },
  {
    "level": 65,
    "name": "羽蛇神",
    "id": 5569,
    "height": 174,
    "face": 0,
    "hair": 13,
    "gender": "女",
    "equipment": {
      "head": "诛神头盔",
      "body": "异形女王甲",
      "hand": "异形骨手套",
      "leg": "诛神腿甲",
      "foot": "异形女王鞋",
      "neck": "战斗狂人军牌",
      "primary": "量子能量枪",
      "secondary1": null,
      "secondary2": null,
      "melee": "诛神短剑",
      "grenade": null
    }
  },
  {
    "level": 50,
    "name": "午夜霓虹",
    "id": 5570,
    "height": 180,
    "face": 1,
    "hair": 16,
    "gender": "男",
    "equipment": {
      "head": "锐刻幻影夜视仪",
      "body": "蓝晶战斗服",
      "hand": "蓝晶手套",
      "leg": "方舟武士腿甲",
      "foot": "幻影装甲鞋",
      "neck": "战斗专家军牌",
      "primary": "战术巴雷特",
      "secondary1": "极品UZI战术版",
      "secondary2": "极品UZI战术版",
      "melee": "光剑天秤",
      "grenade": null
    }
  },
  {
    "level": 36,
    "name": "大枪",
    "id": 5571,
    "height": 177,
    "face": 1,
    "hair": 36,
    "gender": "男",
    "equipment": {
      "head": "精致战术猪鼻式防毒面具",
      "body": "黑色重甲",
      "hand": "61式手甲",
      "leg": "合金腿甲",
      "foot": "61式装甲鞋",
      "neck": "战斗专家军牌",
      "primary": "M134",
      "secondary1": null,
      "secondary2": null,
      "melee": null,
      "grenade": null
    }
  },
  {
    "level": 31,
    "name": "正骨侠",
    "id": 5572,
    "height": 182,
    "face": 1,
    "hair": 7,
    "gender": "男",
    "equipment": {
      "head": "92式头部装甲",
      "body": "幻影胸甲",
      "hand": "92式手甲",
      "leg": "新手裤子##三阶",
      "foot": "幻影装甲鞋",
      "neck": "战斗专家军牌",
      "primary": "QBZ95",
      "secondary1": "LS06",
      "secondary2": "LS06",
      "melee": null,
      "grenade": null
    }
  },
  {
    "level": 60,
    "name": "范马星人",
    "id": 5573,
    "height": 198,
    "face": 1,
    "hair": 17,
    "gender": "男",
    "equipment": {
      "head": "骷髅面具##四阶",
      "body": "兽王虎甲",
      "hand": "诛神手套",
      "leg": "剑圣腿甲",
      "foot": "诛神战鞋",
      "neck": "战斗狂人军牌",
      "primary": null,
      "secondary1": null,
      "secondary2": null,
      "melee": null,
      "grenade": null
    },
    "pricemultiplier": 0.7
  },
  {
    "level": 48,
    "name": "疫医",
    "id": 5574,
    "height": 178,
    "face": 1,
    "hair": 48,
    "gender": "男",
    "equipment": {
      "head": "防毒面具2号##四阶",
      "body": "合金甲",
      "hand": "异形女王手套",
      "leg": "幻影腿甲",
      "foot": "幻影装甲鞋",
      "neck": "未羊项链",
      "primary": null,
      "secondary1": null,
      "secondary2": null,
      "melee": null,
      "grenade": null
    }
  },
  {
    "level": 34,
    "name": "红矮星",
    "id": 5575,
    "height": 190,
    "face": 1,
    "hair": 34,
    "gender": "男",
    "equipment": {
      "head": "61式头部装甲",
      "body": "剑圣胸甲",
      "hand": "剑圣手甲",
      "leg": "61式腿甲",
      "foot": "剑圣装甲鞋",
      "neck": "亥猪项链",
      "primary": "勃朗宁725双管霰弹枪",
      "secondary1": "双管猎枪",
      "secondary2": "双管猎枪",
      "melee": "光斧金牛",
      "grenade": null
    }
  },
  {
    "level": 49,
    "name": "蝰蛇",
    "id": 5576,
    "height": 168,
    "face": 0,
    "hair": 34,
    "gender": "女",
    "equipment": {
      "head": "幻影头部装甲",
      "body": "singer衣服",
      "hand": "keyboard手套",
      "leg": "异形女王腿甲",
      "foot": "黑色高跟皮鞋##四阶",
      "neck": "战斗狂人军牌",
      "primary": "巴雷特",
      "secondary1": null,
      "secondary2": null,
      "melee": "金蛇剑",
      "grenade": null
    },
    "pricemultiplier": 0.6
  },
  {
    "level": 25,
    "name": "海月",
    "id": 5577,
    "height": 162,
    "face": 0,
    "hair": 10,
    "gender": "女",
    "equipment": {
      "head": "黑色X蒙面##二阶",
      "body": "keyboard衣服",
      "hand": "keyboard手套",
      "leg": "新手裤子##二阶",
      "foot": "BOSS2鞋子",
      "neck": "金牌打手项链",
      "primary": "Sniper",
      "secondary1": null,
      "secondary2": "MP7",
      "melee": "虎彻",
      "grenade": null
    }
  },
  {
    "level": 12,
    "name": "黑桃A",
    "id": 5578,
    "height": 157,
    "face": 0,
    "hair": 21,
    "gender": "女",
    "equipment": {
      "head": "新手面具##二阶",
      "body": "SM女王皮衣##二阶",
      "hand": "SM女王黑色皮手套##二阶",
      "leg": "SM女王吊带袜##二阶",
      "foot": "黑色高跟皮鞋##二阶",
      "neck": "调停者军牌",
      "primary": null,
      "secondary1": null,
      "secondary2": null,
      "melee": null,
      "grenade": null
    },
    "pricemultiplier": 0.5
  },
  {
    "level": 14,
    "name": "狂飙",
    "id": 5579,
    "height": 175,
    "face": 1,
    "hair": 17,
    "gender": "男",
    "equipment": {
      "head": "黑色X蒙面##二阶",
      "body": "护肩夹克##二阶",
      "hand": "红色皮手套##二阶",
      "leg": "新手裤子##二阶",
      "foot": "新手皮鞋##二阶",
      "neck": "僵尸割草机军牌",
      "primary": null,
      "secondary1": null,
      "secondary2": "双管猎枪",
      "melee": "砍刀",
      "grenade": null
    }
  },
  {
    "level": 13,
    "name": "刺猬",
    "id": 5580,
    "height": 169,
    "face": 1,
    "hair": 38,
    "gender": "男",
    "equipment": {
      "head": "精致盗贼猪鼻猪鼻式面具",
      "body": "褐色背带背心##二阶",
      "hand": null,
      "leg": "新手裤子##二阶",
      "foot": "褐色简单皮鞋##二阶",
      "neck": "僵尸割草机军牌",
      "primary": "雷明登870",
      "secondary1": null,
      "secondary2": null,
      "melee": "锤子",
      "grenade": null
    }
  },
  {
    "level": 16,
    "name": "讥笑怪咖",
    "id": 5581,
    "height": 175,
    "face": 1,
    "hair": 52,
    "gender": "男",
    "equipment": {
      "head": "杰森面具##二阶",
      "body": "弗莱迪毛衣##二阶",
      "hand": "弗莱迪手套",
      "leg": "金色腰带破洞牛仔裤##二阶",
      "foot": "黑色板鞋",
      "neck": "僵尸割草机军牌",
      "primary": null,
      "secondary1": null,
      "secondary2": null,
      "melee": null,
      "grenade": null
    }
  },
  {
    "level": 20,
    "name": "卤蛋头 零充",
    "id": 5582,
    "height": 180,
    "face": 1,
    "hair": -1,
    "gender": "男",
    "equipment": {
      "head": "红色风镜##二阶",
      "body": "绿色马甲",
      "hand": "红色皮手套##二阶",
      "leg": "墨绿军用下装##二阶",
      "foot": "墨绿军用鞋##二阶",
      "neck": "僵尸克星军牌",
      "primary": null,
      "secondary1": null,
      "secondary2": null,
      "melee": "黑铁重剑枪",
      "grenade": null
    }
  },
  {
    "level": 9,
    "name": "鬼面",
    "id": 5583,
    "height": 160,
    "face": 0,
    "hair": 21,
    "gender": "女",
    "equipment": {
      "head": "骷髅面具",
      "body": "盗贼无袖皮马甲",
      "hand": null,
      "leg": "棕色带腿包短裤",
      "foot": "棕色圆头皮鞋",
      "neck": "新手军牌",
      "primary": null,
      "secondary1": null,
      "secondary2": "TMP",
      "melee": "短斧",
      "grenade": null
    }
  },
  {
    "level": 14,
    "name": "“红手套”",
    "id": 5584,
    "height": 177,
    "face": 1,
    "hair": 16,
    "gender": "男",
    "equipment": {
      "head": "黑色礼帽##二阶",
      "body": "黑色西装##二阶",
      "hand": "红色皮手套#5##二阶",
      "leg": "黑色西装裤##二阶",
      "foot": "黑色军用皮鞋##二阶",
      "neck": "调停者军牌",
      "primary": "汤姆逊冲锋枪",
      "secondary1": null,
      "secondary2": null,
      "melee": "maddog疯狗刀",
      "grenade": null
    }
  },
  {
    "level": 25,
    "name": "手好小哦",
    "id": 5585,
    "height": 175,
    "face": 1,
    "hair": 45,
    "gender": "男",
    "equipment": {
      "head": "棕色墨镜##二阶",
      "body": "黑白女仆装##二阶",
      "hand": "白色手套##二阶",
      "leg": "黑白女仆蕾丝短裙##二阶",
      "foot": "黑色白底皮鞋##二阶",
      "neck": "戌狗项链",
      "primary": "MG42",
      "secondary1": "P90",
      "secondary2": "P90",
      "melee": "西洋重剑枪",
      "grenade": null
    }
  },
  {
    "level": 70,
    "name": "李昂",
    "id": 5586,
    "height": 175,
    "face": 1,
    "hair": -1,
    "gender": "男",
    "equipment": {
      "head": "方舟武士盔",
      "body": "方舟武士甲",
      "hand": "方舟武士手套",
      "leg": "方舟武士腿甲",
      "foot": "方舟武士鞋",
      "neck": "轶事奇人",
      "primary": "远古诛神枪",
      "secondary1": null,
      "secondary2": null,
      "melee": "远古诛神剑",
      "grenade": null
    }
  },
  {
    "level": 57,
    "name": "逆苍天",
    "id": 5587,
    "height": 180,
    "face": 1,
    "hair": 34,
    "gender": "男",
    "equipment": {
      "head": "诛神头盔",
      "body": "诛神胸甲",
      "hand": "诛神手套",
      "leg": "诛神腿甲",
      "foot": "诛神战鞋",
      "neck": "传奇老兵",
      "primary": null,
      "secondary1": null,
      "secondary2": null,
      "melee": "黑铁的剑",
      "grenade": null
    }
  },
  {
    "level": 35,
    "name": "天火",
    "id": 5588,
    "height": 182,
    "face": 1,
    "hair": 2,
    "gender": "男",
    "equipment": {
      "head": "防毒面具2号##四阶",
      "body": "幻影胸甲",
      "hand": "夜行侦查手套",
      "leg": "墨绿军用下装##四阶",
      "foot": "墨绿军用鞋##四阶",
      "neck": "余烬队徽",
      "primary": "Fire Gun",
      "secondary1": null,
      "secondary2": null,
      "melee": null,
      "grenade": null
    }
  },
  {
    "level": 35,
    "name": "苏打",
    "id": 5589,
    "height": 179,
    "face": 1,
    "hair": 41,
    "gender": "男",
    "equipment": {
      "head": "黑铁死士围巾",
      "body": "黑色功夫装##四阶",
      "hand": "幻影手甲",
      "leg": "新手裤子##四阶",
      "foot": "幻影装甲鞋",
      "neck": "余烬队徽",
      "primary": "穿刺QBZ95",
      "secondary1": "双管猎枪",
      "secondary2": "双管猎枪",
      "melee": "中国战刀",
      "grenade": null
    }
  },
  {
    "level": 53,
    "name": "大冤种 牢格雷姆",
    "id": 5590,
    "height": 175,
    "face": 1,
    "hair": 35,
    "gender": "男",
    "equipment": {
      "head": "炎魔盔",
      "body": "炎魔甲",
      "hand": "炎魔手套",
      "leg": "炎魔腿甲",
      "foot": "炎魔鞋",
      "neck": "轶事奇人",
      "primary": "炎魔枪A100",
      "secondary1": "极品UZI战术版",
      "secondary2": "极品UZI战术版",
      "melee": "烈焰斩马刀",
      "grenade": null
    }
  },
  {
    "level": 50,
    "name": "清水結衣酱",
    "id": 5591,
    "height": 150,
    "face": 0,
    "hair": 28,
    "gender": "女",
    "equipment": {
      "head": "61式头部装甲",
      "body": "盗贼纹身装##四阶",
      "hand": "61式手甲",
      "leg": "61式腿甲",
      "foot": "61式装甲鞋",
      "neck": "轶事奇人",
      "primary": null,
      "secondary1": "OPDW17",
      "secondary2": "OPDW17",
      "melee": "上古饮血大太刀",
      "grenade": null
    }
  },
  {
    "level": 29,
    "name": "人狼",
    "id": 5592,
    "height": 185,
    "face": 1,
    "hair": 35,
    "gender": "男",
    "equipment": {
      "head": "92式头部装甲",
      "body": "92式胸甲",
      "hand": "92式手甲",
      "leg": "92式腿甲",
      "foot": "92式装甲鞋",
      "neck": "战斗专家军牌",
      "primary": "MG42",
      "secondary1": "毛瑟手枪",
      "secondary2": "毛瑟手枪",
      "melee": "激光剑",
      "grenade": null
    }
  },
  {
    "level": 20,
    "name": "哥特骇客",
    "id": 5593,
    "height": 153,
    "face": 0,
    "hair": 27,
    "gender": "女",
    "equipment": {
      "head": "仿制A兵团战术猪鼻式防毒面具",
      "body": "guitar衣服",
      "hand": "牛皮手套##二阶",
      "leg": "红色格子短裙##二阶",
      "foot": "红色功夫布鞋##二阶",
      "neck": "金牌打手项链",
      "primary": "KRISS突击版",
      "secondary1": "Mossberg500",
      "secondary2": "Mossberg500",
      "melee": "黑暗吉他",
      "grenade": null
    }
  },
  {
    "level": 100,
    "name": "【幻之羽翼】流年",
    "id": 56,
    "height": 175,
    "face": 1,
    "hair": -1,
    "gender": "男",
    "equipment": {
      "head": "黄金骑士牙狼头盔",
      "body": "黄金骑士牙狼胸甲",
      "hand": "黄金骑士牙狼手套",
      "leg": "黄金骑士牙狼腿甲",
      "foot": "黄金骑士牙狼战鞋",
      "neck": "远古诛神项链",
      "primary": "远古诛神枪",
      "secondary1": "远古诛神短枪",
      "secondary2": "远古诛神短枪",
      "melee": "远古诛神剑",
      "grenade": "压缩胶囊之兽王"
    }
  },
  {
    "level": 100,
    "name": "金色风暴",
    "id": 5594,
    "height": 185,
    "face": 1,
    "hair": 25,
    "gender": "女",
    "equipment": {
      "head": "黄金骑士牙狼头盔#10",
      "body": "盗贼纹身装#13#四阶",
      "hand": "黄金骑士牙狼手套#10",
      "leg": "黄金骑士牙狼腿甲#10",
      "foot": "黄金骑士牙狼战鞋#10",
      "neck": "远古诛神项链#10",
      "primary": "M134暴力版#10",
      "secondary1": null,
      "secondary2": null,
      "melee": null,
      "grenade": null
    }
  },
  {
    "level": 100,
    "name": "牙狼",
    "id": 5595,
    "height": 185,
    "face": 1,
    "hair": -1,
    "gender": "男",
    "equipment": {
      "head": "黄金骑士牙狼头盔#10",
      "body": "黄金骑士牙狼胸甲#10",
      "hand": "黄金骑士牙狼手套#10",
      "leg": "黄金骑士牙狼腿甲#10",
      "foot": "黄金骑士牙狼战鞋#10",
      "neck": "远古诛神项链#10",
      "primary": "诛神枪#13",
      "secondary1": null,
      "secondary2": null,
      "melee": "远古诛神剑#10",
      "grenade": null
    }
  },
  {
    "level": 51,
    "name": "拆迁大队长",
    "id": 5596,
    "height": 185,
    "face": 0,
    "hair": 45,
    "gender": "女",
    "equipment": {
      "head": null,
      "body": "盗贼纹身装##四阶",
      "hand": null,
      "leg": "兽王虎甲腿甲",
      "foot": "远古忍者鞋",
      "neck": "轶事奇人",
      "primary": null,
      "secondary1": null,
      "secondary2": null,
      "melee": "拆迁铁锤",
      "grenade": null
    }
  },
  {
    "level": 23,
    "name": "布偶刺客",
    "id": 5597,
    "height": 151,
    "face": 0,
    "hair": 45,
    "gender": "女",
    "equipment": {
      "head": "白色盗贼猪鼻式防毒面具",
      "body": "战术JK上衣",
      "hand": "牛皮手套##二阶",
      "leg": "战术JK裙",
      "foot": "战术JK鞋子",
      "neck": "金牌打手项链",
      "primary": "MK17",
      "secondary1": "蝎式冲锋枪弹鼓版",
      "secondary2": "蝎式冲锋枪弹鼓版",
      "melee": "汉剑",
      "grenade": null
    }
  },
  {
    "level": 35,
    "name": "兵长",
    "id": 5598,
    "height": 160,
    "face": 1,
    "hair": 7,
    "gender": "男",
    "equipment": {
      "head": null,
      "body": "风衣战术服",
      "hand": "牛仔手套",
      "leg": "牛仔裤子",
      "foot": "牛仔皮鞋",
      "neck": "轶事奇人",
      "primary": "TTI Benelli M4",
      "secondary1": "穿刺LS06",
      "secondary2": "穿刺LS06",
      "melee": "超硬质双刀",
      "grenade": null
    }
  },
  {
    "level": 12,
    "name": "洋葱头",
    "id": 5599,
    "height": 158,
    "face": 1,
    "hair": 36,
    "gender": "男",
    "equipment": {
      "head": "白色盗贼猪鼻式防毒面具",
      "body": "浅灰背心##二阶",
      "hand": "黑色皮手套##二阶",
      "leg": "墨绿军用下装##二阶",
      "foot": "墨绿军用鞋##二阶",
      "neck": "新手军牌",
      "primary": null,
      "secondary1": "双管猎枪",
      "secondary2": null,
      "melee": "铁钉球棒",
      "grenade": null
    }
  },
  {
    "level": 66,
    "name": "真-逆天剑客",
    "id": 5600,
    "height": 181,
    "face": 1,
    "hair": -1,
    "gender": "男",
    "equipment": {
      "head": "钛合金61式头部装甲",
      "body": "钛合金61式胸甲",
      "hand": "钛合金61式手甲",
      "leg": "钛合金61式腿甲",
      "foot": "钛合金61式装甲鞋",
      "neck": "传奇老兵",
      "primary": "M134暴力版",
      "secondary1": "钛合金P90",
      "secondary2": "钛合金P90",
      "melee": "血色光剑天秤",
      "grenade": null
    }
  },
  {
    "level": 31,
    "name": "寒风",
    "id": 5601,
    "height": 170,
    "face": 1,
    "hair": 26,
    "gender": "男",
    "equipment": {
      "head": "次品蓝晶面具",
      "body": "次品蓝晶战斗服",
      "hand": "次品蓝晶手套",
      "leg": "次品蓝晶下装",
      "foot": "次品蓝晶鞋",
      "neck": "角斗高手项链",
      "primary": "巨兽",
      "secondary1": null,
      "secondary2": null,
      "melee": "冰魄斩",
      "grenade": null
    }
  },
  {
    "level": 41,
    "name": "冬狮娘",
    "id": 5602,
    "height": 178,
    "face": 0,
    "hair": 22,
    "gender": "女",
    "equipment": {
      "head": "次品蓝晶面具",
      "body": "次品蓝晶战斗服",
      "hand": "次品蓝晶手套",
      "leg": "次品蓝晶下装",
      "foot": "次品蓝晶鞋",
      "neck": "角斗高手项链",
      "primary": "巨兽",
      "secondary1": null,
      "secondary2": null,
      "melee": "冰魄斩",
      "grenade": null
    }
  },
  {
    "level": 41,
    "name": "炏",
    "id": 5603,
    "height": 182,
    "face": 1,
    "hair": 5,
    "gender": "男",
    "equipment": {
      "head": "合金盔",
      "body": "合金甲",
      "hand": "合金手套",
      "leg": "合金腿甲",
      "foot": "合金鞋",
      "neck": "角斗高手项链",
      "primary": "烈焰枪A100",
      "secondary1": null,
      "secondary2": null,
      "melee": "烈焰斩",
      "grenade": null
    }
  },
  {
    "level": 36,
    "name": "火",
    "id": 5604,
    "height": 162,
    "face": 0,
    "hair": 21,
    "gender": "女",
    "equipment": {
      "head": "合金盔",
      "body": "合金甲",
      "hand": "合金手套",
      "leg": "合金腿甲",
      "foot": "合金鞋",
      "neck": "角斗高手项链",
      "primary": "烈焰枪B100",
      "secondary1": null,
      "secondary2": null,
      "melee": "烈焰斩",
      "grenade": null
    },
    "pricemultiplier": 1.2
  },
  {
    "level": 45,
    "name": " Sub-Zero",
    "id": 5605,
    "height": 170,
    "face": 1,
    "hair": 44,
    "gender": "男",
    "equipment": {
      "head": "蓝晶面具",
      "body": "次品蓝晶战斗服",
      "hand": "次品蓝晶手套",
      "leg": "次品蓝晶下装",
      "foot": "蓝晶鞋",
      "neck": "角斗王者项链",
      "primary": "诺亚方舟护士狙击步枪",
      "secondary1": null,
      "secondary2": null,
      "melee": "冰魄神斩",
      "grenade": null
    },
    "pricemultiplier": 1.2
  },
  {
    "level": 33,
    "name": "北极",
    "id": 5606,
    "height": 178,
    "face": 0,
    "hair": 51,
    "gender": "女",
    "equipment": {
      "head": "次品蓝晶面具",
      "body": "次品蓝晶战斗服",
      "hand": "次品蓝晶手套",
      "leg": "次品蓝晶下装",
      "foot": "次品蓝晶鞋",
      "neck": "角斗高手项链",
      "primary": "巨兽",
      "secondary1": null,
      "secondary2": null,
      "melee": "冰魄斩",
      "grenade": null
    }
  },
  {
    "level": 44,
    "name": "㷋",
    "id": 5607,
    "height": 182,
    "face": 1,
    "hair": 5,
    "gender": "男",
    "equipment": {
      "head": "合金盔",
      "body": "合金甲",
      "hand": "合金手套",
      "leg": "合金腿甲",
      "foot": "合金鞋",
      "neck": "角斗高手项链",
      "primary": "烈焰枪A100",
      "secondary1": null,
      "secondary2": null,
      "melee": "烈焰斩",
      "grenade": null
    }
  },
  {
    "level": 46,
    "name": "燚",
    "id": 5608,
    "height": 162,
    "face": 0,
    "hair": 21,
    "gender": "女",
    "equipment": {
      "head": "合金盔",
      "body": "合金甲",
      "hand": "合金手套",
      "leg": "合金腿甲",
      "foot": "合金鞋",
      "neck": "角斗高手项链",
      "primary": "烈焰枪B100",
      "secondary1": null,
      "secondary2": null,
      "melee": "烈焰斩",
      "grenade": null
    }
  },
  {
    "level": 45,
    "name": "焱",
    "id": 5609,
    "height": 162,
    "face": 0,
    "hair": 21,
    "gender": "女",
    "equipment": {
      "head": "合金盔",
      "body": "合金甲",
      "hand": "合金手套",
      "leg": "合金腿甲",
      "foot": "合金鞋",
      "neck": "角斗高手项链",
      "primary": "烈焰枪B100",
      "secondary1": null,
      "secondary2": null,
      "melee": "烈焰斩",
      "grenade": null
    }
  },
  {
    "level": 38,
    "name": "灬",
    "id": 5610,
    "height": 182,
    "face": 1,
    "hair": 5,
    "gender": "男",
    "equipment": {
      "head": "合金盔",
      "body": "合金甲",
      "hand": "合金手套",
      "leg": "合金腿甲",
      "foot": "合金鞋",
      "neck": "角斗高手项链",
      "primary": "烈焰枪A100",
      "secondary1": null,
      "secondary2": null,
      "melee": "烈焰斩",
      "grenade": null
    },
    "pricemultiplier": 1.2
  },
  {
    "level": 100,
    "name": "土豪猪",
    "id": 5612,
    "height": 155,
    "face": 1,
    "hair": -1,
    "gender": "男",
    "equipment": {
      "head": "黄金骑士牙狼头盔#10",
      "body": "黄金骑士牙狼胸甲#10",
      "hand": "黄金骑士牙狼手套#10",
      "leg": "黄金骑士牙狼腿甲#10",
      "foot": "黄金骑士牙狼战鞋#10",
      "neck": "亥猪项链#10",
      "primary": "黄金QBZ#13",
      "secondary1": "MP7极品战术版#13",
      "secondary2": "MP7极品战术版#13",
      "melee": "金蛇剑#13",
      "grenade": null
    }
  },
  {
    "level": 50,
    "name": "千夏沐晓酱",
    "id": 5613,
    "height": 150,
    "face": 0,
    "hair": 45,
    "gender": "女",
    "equipment": {
      "head": "蓝晶面具",
      "body": "蓝晶战斗服",
      "hand": "蓝晶手套",
      "leg": "蓝晶下装",
      "foot": "战术JK鞋子",
      "neck": "轶事奇人",
      "primary": "高斯枪",
      "secondary1": null,
      "secondary2": null,
      "melee": "热能武士刀",
      "grenade": null
    }
  },
  {
    "level": 100,
    "name": "千重岳",
    "id": 5614,
    "height": 200,
    "face": 1,
    "hair": 7,
    "gender": "男",
    "equipment": {
      "head": "兽王战甲盔#10",
      "body": "兽王战甲#10",
      "hand": "兽王战甲手套#13",
      "leg": "兽王战甲腿甲#10",
      "foot": "兽王战甲鞋#10",
      "neck": "空手大加成项链#13",
      "primary": null,
      "secondary1": null,
      "secondary2": null,
      "melee": null,
      "grenade": null
    }
  },
  {
    "level": 100,
    "name": "狼王",
    "id": 5615,
    "height": 173,
    "face": 0,
    "hair": 45,
    "gender": "女",
    "equipment": {
      "head": "芬里尔头甲#13",
      "body": "芬里尔胸甲#13",
      "hand": "芬里尔手甲#13",
      "leg": "芬里尔腿甲#13",
      "foot": "芬里尔鞋#13",
      "neck": "诛神项链#10",
      "primary": "紫色幻想#10",
      "secondary1": "轻量化量子能量枪#10",
      "secondary2": "轻量化量子能量枪#10",
      "melee": "绝地武士佩剑#10",
      "grenade": null
    }
  },
  {
    "level": 60,
    "name": "板齿犀",
    "id": 5616,
    "height": 195,
    "face": 1,
    "hair": 20,
    "gender": "男",
    "equipment": {
      "head": "试作型原种共生头盔",
      "body": "试作型原种共生上装",
      "hand": "试作型原种共生手套",
      "leg": "试作型原种共生下装",
      "foot": "试作型原种共生鞋",
      "neck": "戌狗项链",
      "primary": null,
      "secondary1": null,
      "secondary2": null,
      "melee": null,
      "grenade": null
    }
  },
  {
    "level": 60,
    "name": "爪王",
    "id": 5617,
    "height": 187,
    "face": 0,
    "hair": 47,
    "gender": "女",
    "equipment": {
      "head": "异形女王盔",
      "body": "异形女王甲",
      "hand": "异形女王手套",
      "leg": "异形女王腿甲",
      "foot": "异形女王鞋",
      "neck": "空手中加成项链",
      "primary": null,
      "secondary1": null,
      "secondary2": null,
      "melee": null,
      "grenade": null
    }
  },
  {
    "level": 50,
    "name": "利爪",
    "id": 5618,
    "height": 162,
    "face": 1,
    "hair": 17,
    "gender": "男",
    "equipment": {
      "head": "异形骨盔",
      "body": "异形骨甲",
      "hand": "异形骨手套",
      "leg": "异形骨腿甲",
      "foot": "异形骨鞋",
      "neck": "空手小加成项链",
      "primary": null,
      "secondary1": null,
      "secondary2": null,
      "melee": null,
      "grenade": null
    }
  },
  {
    "level": 70,
    "name": "巨狼",
    "id": 5619,
    "height": 197,
    "face": 1,
    "hair": 3,
    "gender": "男",
    "equipment": {
      "head": "芬里尔头甲",
      "body": "芬里尔胸甲",
      "hand": "芬里尔手甲",
      "leg": "芬里尔腿甲",
      "foot": "芬里尔鞋",
      "neck": "冷兵器大加成项链",
      "primary": "能量狙击枪",
      "secondary1": "改造式诺亚科技冲锋枪",
      "secondary2": "改造式诺亚科技冲锋枪",
      "melee": "诛神剑",
      "grenade": null
    }
  },
  {
    "level": 52,
    "name": "莱特宁",
    "id": 5620,
    "height": 187,
    "face": 0,
    "hair": 27,
    "gender": "女",
    "equipment": {
      "head": "重甲头部",
      "body": "重甲上衣",
      "hand": "重甲手套",
      "leg": "重甲裤子",
      "foot": "重甲鞋子",
      "neck": "枪械大加成项链",
      "primary": "诛神枪",
      "secondary1": null,
      "secondary2": null,
      "melee": "激光剑",
      "grenade": null
    }
  },
  {
    "level": 43,
    "name": "热电阻",
    "id": 5621,
    "height": 166,
    "face": 1,
    "hair": 2,
    "gender": "男",
    "equipment": {
      "head": "重甲头部",
      "body": "重甲上衣",
      "hand": "重甲手套",
      "leg": "重甲裤子",
      "foot": "重甲鞋子",
      "neck": "枪械中加成项链",
      "primary": "龙炎",
      "secondary1": "爆炎蒸汽",
      "secondary2": "爆炎蒸汽",
      "melee": "热能武士刀",
      "grenade": null
    }
  },
  {
    "level": 58,
    "name": "毒壳",
    "id": 5622,
    "height": 176,
    "face": 1,
    "hair": 2,
    "gender": "男",
    "equipment": {
      "head": "重甲头部",
      "body": "重甲上衣",
      "hand": "重甲手套",
      "leg": "重甲裤子",
      "foot": "重甲鞋子",
      "neck": "战斗狂人军牌",
      "primary": "毒蛛",
      "secondary1": null,
      "secondary2": null,
      "melee": "猎杀巨物大锤",
      "grenade": null
    }
  },
  {
    "level": 35,
    "name": "老朋友",
    "id": 5623,
    "height": 175,
    "face": 0,
    "hair": 1,
    "gender": "男",
    "equipment": {
      "head": "夜行侦查盔",
      "body": "夜行侦查上装",
      "hand": "夜行侦查手套",
      "leg": "夜行侦查下装",
      "foot": "夜行侦查鞋",
      "neck": "前朝遗老",
      "primary": "HK53",
      "secondary1": "FR506",
      "secondary2": "FR506",
      "melee": "周波匕首",
      "grenade": null
    },
    "pricemultiplier": 1.5
  },
  {
    "level": 40,
    "name": "亚瑟摩根",
    "id": 5625,
    "height": 180,
    "face": 1,
    "hair": 33,
    "gender": "男",
    "equipment": {
      "head": "牛仔风帽",
      "body": "牛仔上衣",
      "hand": "牛仔手套",
      "leg": "牛仔裤子",
      "foot": "牛仔皮鞋",
      "neck": "枪械大加成项链",
      "primary": "牛仔的温切斯特",
      "secondary1": "牛仔的左轮",
      "secondary2": "牛仔的左轮",
      "melee": "光刃摩羯",
      "grenade": null
    }
  },
  {
    "level": 17,
    "name": "侵蚀",
    "id": 5626,
    "height": 170,
    "face": 1,
    "hair": 9,
    "gender": "男",
    "equipment": {
      "head": "锐刻幻影夜视仪",
      "body": "C级防化服上装",
      "hand": "C级防化服手套",
      "leg": "C级防化服下装",
      "foot": "C级防化服鞋",
      "neck": "地球卫士项链",
      "primary": "MK17",
      "secondary1": "蝎式冲锋枪弹鼓版",
      "secondary2": "蝎式冲锋枪弹鼓版",
      "melee": "铁杆长矛",
      "grenade": null
    }
  },
  {
    "level": 27,
    "name": "前清道夫",
    "id": 5627,
    "height": 175,
    "face": 0,
    "hair": 22,
    "gender": "女",
    "equipment": {
      "head": "B级防化服头套",
      "body": "B级防化服上装",
      "hand": "B级防化服手套",
      "leg": "B级防化服下装",
      "foot": "B级防化服鞋",
      "neck": "A兵团精致项链",
      "primary": null,
      "secondary1": "vactorPP-7400U",
      "secondary2": "vactorPP-7400U",
      "melee": "剧毒银刃",
      "grenade": null
    }
  },
  {
    "level": 37,
    "name": "前A级清道夫",
    "id": 5628,
    "height": 190,
    "face": 1,
    "hair": 15,
    "gender": "男",
    "equipment": {
      "head": "A级防化服头套",
      "body": "A级防化服上装",
      "hand": "A级防化服手套",
      "leg": "A级防化服下装",
      "foot": "A级防化服鞋",
      "neck": "战斗狂人军牌",
      "primary": "Fire Gun",
      "secondary1": null,
      "secondary2": null,
      "melee": "斩龙剑",
      "grenade": null
    }
  },
  {
    "level": 56,
    "name": "白绝",
    "id": 5629,
    "height": 180,
    "face": 0,
    "hair": 45,
    "gender": "女",
    "equipment": {
      "head": "远古忍者盔",
      "body": "远古忍者甲",
      "hand": "远古忍者手套",
      "leg": "远古忍者腿甲",
      "foot": "远古忍者鞋",
      "neck": "未羊项链",
      "primary": "战术巴雷特",
      "secondary1": null,
      "secondary2": null,
      "melee": "忍者执剑",
      "grenade": null
    }
  },
  {
    "level": 20,
    "name": "大卫",
    "id": 5630,
    "height": 176,
    "face": 1,
    "hair": 54,
    "gender": "男",
    "equipment": {
      "head": "特战队员头部装备",
      "body": "特战队员战术背心",
      "hand": "特战队员手套",
      "leg": "特战队员战术裤",
      "foot": "特战队员鞋子",
      "neck": "冷兵器小加成项链",
      "primary": "XM1014",
      "secondary1": null,
      "secondary2": null,
      "melee": "斩马刀",
      "grenade": null
    }
  },
  {
    "level": 20,
    "name": "瑞秋",
    "id": 5631,
    "height": 165,
    "face": 0,
    "hair": 46,
    "gender": "女",
    "equipment": {
      "head": "特战队员头部装备",
      "body": "特战队员战术背心",
      "hand": "特战队员手套",
      "leg": "特战队员战术裤",
      "foot": "特战队员鞋子",
      "neck": "枪械小加成项链",
      "primary": null,
      "secondary1": "MP5战术版",
      "secondary2": "MP5战术版",
      "melee": "战术黑刀",
      "grenade": null
    }
  },
  {
    "level": 33,
    "name": "沛多多",
    "id": 5632,
    "height": 169,
    "face": 1,
    "hair": 7,
    "gender": "男",
    "equipment": {
      "head": "61式头部装甲",
      "body": "61式胸甲",
      "hand": "61式手甲",
      "leg": "61式腿甲",
      "foot": "61式装甲鞋",
      "neck": "接触者军牌",
      "primary": "MG42",
      "secondary1": null,
      "secondary2": null,
      "melee": "光斧金牛",
      "grenade": null
    }
  },
  {
    "level": 33,
    "name": "约翰Top灬红人馆",
    "id": 5633,
    "height": 175,
    "face": 1,
    "hair": 8,
    "gender": "男",
    "equipment": {
      "head": "61式头部装甲",
      "body": "61式胸甲",
      "hand": "61式手甲",
      "leg": "61式腿甲",
      "foot": "61式装甲鞋",
      "neck": "接触者军牌",
      "primary": "M249",
      "secondary1": "P90",
      "secondary2": "P90",
      "melee": "光剑天秤",
      "grenade": null
    }
  },
  {
    "level": 70,
    "name": "你是？",
    "id": 5634,
    "height": 175,
    "face": 1,
    "hair": 44,
    "gender": "男",
    "equipment": {
      "head": "战术猪鼻式防毒面具",
      "body": "A兵团制式战术背心",
      "hand": "A兵团制式战术手套",
      "leg": "A兵团制式战术裤",
      "foot": "A兵团制式战术皮鞋",
      "neck": "通关证明",
      "primary": "SPAS12",
      "secondary1": "MP7",
      "secondary2": "韦森686",
      "melee": "虎彻",
      "grenade": null
    },
    "pricemultiplier": 3.0,
	"passive":{
      "拳脚攻击":{"技能名":"拳脚攻击", "等级":10, "启用":true},
      "升龙拳":{"技能名":"升龙拳", "等级":10, "启用":true},
      "裂地拳":{"技能名":"裂地拳", "等级":10, "启用":true},
      "刀剑攻击":{"技能名":"刀剑攻击", "等级":10, "启用":true},
      "上挑":{"技能名":"上挑", "等级":10, "启用":true},
      "下劈":{"技能名":"下劈", "等级":10, "启用":true},
      "枪械攻击":{"技能名":"枪械攻击", "等级":10, "启用":true},
      "枪械师":{"技能名":"枪械师", "等级":10, "启用":true},
      "冲击连携":{"技能名":"冲击连携", "等级":10, "启用":true},
      "内力爆发":{"技能名":"内力爆发", "等级":10, "启用":true},
      "独行者":{"技能名":"独行者", "等级":10, "启用":true}
    },
    "hidden": true
  },
  {
    "level": 70,
    "name": "自由骑士",
    "id": 5635,
    "height": 185,
    "face": 0,
    "hair": 27,
    "gender": "女",
    "equipment": {
      "head": "自由骑士头甲",
      "body": "自由骑士胸甲",
      "hand": "自由骑士手甲",
      "leg": "自由骑士腿甲",
      "foot": "自由骑士鞋",
      "neck": "诛神项链",
      "primary": "",
      "secondary1": "",
      "secondary2": "",
      "melee": "流星枪",
      "grenade": null
    }
  },
  {
    "level": 100,
    "name": "剑仙",
    "id": 5636,
    "height": 169,
    "face": 1,
    "hair": 17,
    "gender": "男",
    "equipment": {
      "head": "自由骑士头甲#10",
      "body": "自由骑士胸甲#10",
      "hand": "自由骑士手甲#10",
      "leg": "自由骑士腿甲#10",
      "foot": "自由骑士鞋#10",
      "neck": "冷兵器大加成项链#13",
      "primary": "",
      "secondary1": "",
      "secondary2": "",
      "melee": "审判日夜闪#13",
      "grenade": null
    }
  },
  {
    "level": 70,
    "name": "北哥",
    "id": 5637,
    "height": 188,
    "face": 1,
    "hair": 6,
    "gender": "男",
    "equipment": {
      "head": "黑犀头甲",
      "body": "黑犀胸甲",
      "hand": "黑犀手甲",
      "leg": "黑犀腿甲",
      "foot": "黑犀鞋",
      "neck": "空手大加成项链",
      "primary": "",
      "secondary1": "",
      "secondary2": "",
      "melee": "",
      "grenade": null
    }
  },
  {
    "level": 100,
    "name": "黑犀侠",
    "id": 5638,
    "height": 188,
    "face": 1,
    "hair": 6,
    "gender": "男",
    "equipment": {
      "head": "黑犀头甲#10",
      "body": "黑犀胸甲#10",
      "hand": "黑犀手甲#13",
      "leg": "黑犀腿甲#103",
      "foot": "黑犀鞋#10",
      "neck": "地球卫士项链#13",
      "primary": "",
      "secondary1": "",
      "secondary2": "",
      "melee": "流星枪#13",
      "grenade": null
    }
  },
  {
    "level": 30,
    "name": "MASTERSON",
    "id": 5639,
    "height": 180,
    "face": 1,
    "hair": 4,
    "gender": "男",
    "equipment": {
      "head": "废城军装帽#7",
      "body": "废城防弹军装上装#7",
      "hand": "废城军装手套#7",
      "leg": "废城军装下装#7",
      "foot": "废城军装鞋#7",
      "neck": "克隆体#7",
      "primary": "L85A1#7",
      "secondary1": "m9#7",
      "secondary2": "m9#7",
      "melee": "匕首",
      "grenade": null
    },
    "pricemultiplier": 2.5,
	"passive":{
      "拳脚攻击":{"技能名":"拳脚攻击", "等级":5, "启用":true},
      "升龙拳":{"技能名":"升龙拳", "等级":5, "启用":true},
      "裂地拳":{"技能名":"裂地拳", "等级":5, "启用":true},
      "刀剑攻击":{"技能名":"刀剑攻击", "等级":5, "启用":true},
      "上挑":{"技能名":"上挑", "等级":5, "启用":true},
      "下劈":{"技能名":"下劈", "等级":5, "启用":true},
      "枪械攻击":{"技能名":"枪械攻击", "等级":5, "启用":true},
      "枪械师":{"技能名":"枪械师", "等级":5, "启用":true},
      "冲击连携":{"技能名":"冲击连携", "等级":5, "启用":true},
      "独行者":{"技能名":"独行者", "等级":10, "启用":true}
    },
    "hidden": true
  },
  {
    "level": 7,
    "name": "兵痞",
    "id": 5640,
    "height": 165,
    "face": 1,
    "hair": 4,
    "gender": "男",
    "equipment": {
      "head": "废城军装帽",
      "body": "废城军装上装",
      "hand": "废城军装手套",
      "leg": "废城军装下装",
      "foot": "废城军装鞋",
      "neck": "僵尸割草机军牌",
      "primary": "L85A1",
      "secondary1": "m9",
      "secondary2": null,
      "melee": "匕首",
      "grenade": null
    }
  },
  {
    "level": 15,
    "name": "扫地工",
    "id": 5641,
    "height": 175,
    "face": 1,
    "hair": 4,
    "gender": "男",
    "equipment": {
      "head": "废城军装面具帽",
      "body": "废城防弹军装上装",
      "hand": "废城加强军装手套",
      "leg": "废城加强军装下装",
      "foot": "废城加强军装脚",
      "neck": "僵尸克星军牌",
      "primary": "M3 Rocket Launcher",
      "secondary1": "双管猎枪",
      "secondary2": null,
      "melee": "消防斧",
      "grenade": null
    }
  },
  {
    "level": 18,
    "name": "跟踪狂滚出去",
    "id": 5642,
    "height": 170,
    "face": 1,
    "hair": 4,
    "gender": "女",
    "equipment": {
      "head": "废城军装面具帽",
      "body": "废城防弹军装上装",
      "hand": "废城军装手套",
      "leg": "废城军装下装",
      "foot": "废城军装鞋",
      "neck": "轶事奇人",
      "primary": "AKS74U",
      "secondary1": "APSstechkin",
      "secondary2": null,
      "melee": "兰博2",
      "grenade": null
    }
  },
  {
    "level": 15,
    "name": "地上拳王",
    "id": 5643,
    "height": 180,
    "face": 1,
    "hair": 40,
    "gender": "男",
    "equipment": {
      "head": null,
      "body": null,
      "hand": "大型拳套",
      "leg": "天山黑侠裤子",
      "foot": "天山黑侠棕色皮鞋",
      "neck": "空手小加成项链",
      "primary": null,
      "secondary1": null,
      "secondary2": null,
      "melee": null,
      "grenade": null
    }
  },
  {
    "level": 26,
    "name": "半感染者",
    "id": 5645,
    "height": 199,
    "face": 0,
    "hair": 26,
    "gender": "女",
    "equipment": {
      "head": "般若赤鬼半覆面",
      "body": "剑圣胸甲",
      "hand": "黑光重锤",
      "leg": "LEE战服下装",
      "foot": "LEE战靴",
      "neck": "空手中加成项链",
      "primary": null,
      "secondary1": null,
      "secondary2": null,
      "melee": null,
      "grenade": null
    }
  },
  {
    "level": 100,
    "name": "泰坦",
    "id": 5646,
    "height": 218,
    "face": 1,
    "hair": 0,
    "gender": "男",
    "equipment": {
      "head": "觉醒者.L33T墨镜#13",
      "body": "黄金骑士牙狼胸甲#13",
      "hand": "末日铁拳#13",
      "leg": "黄金骑士牙狼腿甲#13",
      "foot": "黄金骑士牙狼战鞋#13",
      "neck": "空手大加成项链#13",
      "primary": "",
      "secondary1": "",
      "secondary2": "",
      "melee": "",
      "grenade": null
    }
  },
  {
    "level": 70,
    "name": "艾萨克",
    "id": 5647,
    "height": 176,
    "face": 1,
    "hair": 4,
    "gender": "男",
    "equipment": {
      "head": "先进防护服头甲",
      "body": "先进防护服胸甲",
      "hand": "先进防护服手甲",
      "leg": "先进防护服腿甲",
      "foot": "先进防护服鞋",
      "neck": "生存者军牌",
      "primary": "等离子切割机",
      "secondary1": "",
      "secondary2": "",
      "melee": "",
      "grenade": null
    }
  },
  {
    "level": 100,
    "name": "枪神",
    "id": 5648,
    "height": 169,
    "face": 1,
    "hair": 2,
    "gender": "男",
    "equipment": {
      "head": "先进防护服头甲#10",
      "body": "先进防护服胸甲#10",
      "hand": "先进防护服手甲#10",
      "leg": "先进防护服腿甲#10",
      "foot": "先进防护服鞋#10",
      "neck": "枪械大加成项链#13",
      "primary": "紫色幻想#13",
      "secondary1": "改造式诺亚科技冲锋枪#13",
      "secondary2": "改造式诺亚科技冲锋枪#13",
      "melee": "",
      "grenade": null
    }
  },
  {
    "level": 100,
    "name": "六耳",
    "id": 5649,
    "height": 160,
    "face": 1,
    "hair": 8,
    "gender": "男",
    "equipment": {
      "head": "大圣头甲#13",
      "body": "大圣上装#13",
      "hand": "大圣手甲#13",
      "leg": "大圣下装#13",
      "foot": "大圣鞋#13",
      "neck": "申猴项链#13",
      "primary": "",
      "secondary1": "",
      "secondary2": "",
      "melee": "如意金箍棒（仿）#10",
      "grenade": null
    }
  },
  {
    "level": 100,
    "name": "波多尔多",
    "id": 5650,
    "height": 189,
    "face": 1,
    "hair": 7,
    "gender": "男",
    "equipment": {
      "head": "登上明星#13",
      "body": "贯空天盖上衣#13",
      "hand": "贯空天盖手套#13",
      "leg": "贯空天盖下衣#13",
      "foot": "贯空天盖长靴#13",
      "neck": "爱心勋章#13",
      "primary": "",
      "secondary1": "",
      "secondary2": "",
      "melee": "",
      "grenade": null
    }
  },
  {
    "level": 70,
    "name": "祈手",
    "id": 5651,
    "height": 171,
    "face": 1,
    "hair": 9,
    "gender": "男",
    "equipment": {
      "head": "登上明星",
      "body": "贯空天盖上衣",
      "hand": "贯空天盖手套",
      "leg": "贯空天盖下衣",
      "foot": "贯空天盖长靴",
      "neck": "接触者军牌#13",
      "primary": "战术版喷火器",
      "secondary1": "",
      "secondary2": "",
      "melee": "异形女王毒刺",
      "grenade": null
    }
  },
  {
    "level": 52,
    "name": "虎妙",
    "id": 5652,
    "height": 155,
    "face": 0,
    "hair": 76,
    "gender": "女",
    "equipment": {
      "head": "真猫妖头套#10",
      "body": "真猫妖背心#10",
      "hand": "真猫妖手套#10",
      "leg": "真猫妖短裤#10",
      "foot": "真猫妖皮鞋#10",
      "neck": "空手大加成项链#10",
      "primary": "",
      "secondary1": "",
      "secondary2": "",
      "melee": "",
      "grenade": null
    },
    "pricemultiplier": 2.5,
    "passive":{
      "拳脚攻击":{"技能名":"拳脚攻击", "等级":10, "启用":true},
      "内力爆发":{"技能名":"内力爆发", "等级":10, "启用":true},
      "独行者":{"技能名":"独行者", "等级":10, "启用":true}
    }
  },
  {
    "level": 39,
    "name": "街头英雄",
    "id": 5653,
    "height": 178,
    "face": 1,
    "hair": 74,
    "gender": "男",
    "equipment": {
      "head": "毒液蜘蛛侠头套",
      "body": "毒液蜘蛛侠战服上装",
      "hand": "毒液蜘蛛侠战服手套",
      "leg": "毒液蜘蛛侠战服下装",
      "foot": "毒液蜘蛛侠战靴",
      "neck": "守护者军牌",
      "primary": "",
      "secondary1": "",
      "secondary2": "",
      "melee": "",
      "grenade": null
    }
  },
  {
    "level": 38,
    "name": "蜘蛛女侠",
    "id": 5655,
    "height": 173,
    "face": 0,
    "hair": 27,
    "gender": "女",
    "equipment": {
      "head": "毒液蜘蛛侠头套",
      "body": "毒液蜘蛛侠战服上装",
      "hand": "毒液蜘蛛侠战服手套",
      "leg": "毒液蜘蛛侠战服下装",
      "foot": "毒液蜘蛛侠战靴",
      "neck": "战斗专家军牌",
      "primary": "",
      "secondary1": "",
      "secondary2": "",
      "melee": "",
      "grenade": null
    }
  },
  {
    "level": 47,
    "name": "马老板",
    "id": 5656,
    "height": 182,
    "face": 1,
    "hair": 64,
    "gender": "男",
    "equipment": {
      "head": "Mark3头甲",
      "body": "Mark3胸甲",
      "hand": "Mark3手甲",
      "leg": "Mark3腿甲",
      "foot": "Mark3鞋",
      "neck": "K5项链",
      "primary": "RPG28",
      "secondary1": "",
      "secondary2": "",
      "melee": "",
      "grenade": null
    }
  }
]