<DOMSymbolItem xmlns:xsi="http://www.w3.org/2001/XMLSchema-instance" xmlns="http://ns.adobe.com/xfl/2008/" name="Symbol 292" itemID="6577f221-00000a13" symbolType="graphic" lastModified="1701332846">
  <timeline>
    <DOMTimeline name="Symbol 292">
      <layers>
        <DOMLayer name="Layer 1" color="#4F4FFF" current="true" isSelected="true">
          <frames>
            <DOMFrame index="0" motionTweenScale="false" keyMode="8192">
              <elements>
                <DOMShape isFloating="true">
                  <fills>
                    <FillStyle index="1">
                      <SolidColor color="#643E33"/>
                    </FillStyle>
                    <FillStyle index="2">
                      <SolidColor color="#A46C5B"/>
                    </FillStyle>
                  </fills>
                  <strokes>
                    <StrokeStyle index="1">
                      <SolidStroke scaleMode="normal">
                        <fill>
                          <SolidColor/>
                        </fill>
                      </SolidStroke>
                    </StrokeStyle>
                  </strokes>
                  <edges>
                    <Edge fillStyle0="1" strokeStyle="1" edges="!-1459 1386[-1435 1281 -1439 1184!-1439 1184[-1459 1235 -1505 1220!-1505 1220[-1602 1185 -1706 1376!-1706 1376|-1799 1389!-1799 1389|-1869 1334!-1869 1334|-1957 1250"/>
                    <Edge fillStyle0="1" edges="!-1957 1250|-1961 1246!-1961 1246[-2060 1132 -2132 1183!-2132 1183[-2203 1233 -2239 1292!-2239 1292|-2252 1329!-2252 1329[-2270 1383 -2242 1452!-2242 1452[-2216 1521 -2116 1583"/>
                    <Edge fillStyle0="1" strokeStyle="1" edges="!-2116 1583[-2112 1585 -2107 1588"/>
                    <Edge fillStyle0="1" fillStyle1="2" edges="!-2107 1588|-2155 1525!-2155 1525[-2276 1377 -2149 1300!-2149 1300[-2036 1240 -1914 1353!-1914 1353|-1818 1436!-1818 1436[-1750 1452 -1664 1410!-1664 1410[-1587 1315 -1520 1314!-1520 1314[-1452 1322 -1459 1386"/>
                    <Edge fillStyle1="2" strokeStyle="1" edges="!-1459 1386[-1475 1454 -1503 1527!-1503 1527[-1512 1548 -1540 1560!-1540 1560[-1632 1602 -1756 1673!-1756 1673[-1842 1727 -1896 1699!-1896 1699|-1973 1661!-1973 1661|-2107 1588"/>
                  </edges>
                </DOMShape>
              </elements>
            </DOMFrame>
          </frames>
        </DOMLayer>
        <DOMLayer name="Layer 2" color="#4F4FFF">
          <frames>
            <DOMFrame index="0" motionTweenScale="false" keyMode="8192">
              <elements>
                <DOMShape isFloating="true">
                  <fills>
                    <FillStyle index="1">
                      <SolidColor color="#643E33"/>
                    </FillStyle>
                    <FillStyle index="2">
                      <SolidColor color="#A46C5B"/>
                    </FillStyle>
                  </fills>
                  <strokes>
                    <StrokeStyle index="1">
                      <SolidStroke scaleMode="normal">
                        <fill>
                          <SolidColor/>
                        </fill>
                      </SolidStroke>
                    </StrokeStyle>
                  </strokes>
                  <edges>
                    <Edge fillStyle0="1" strokeStyle="1" edges="!-1281 1474[-1255 1371 -1256 1273!-1256 1273[-1277 1324 -1324 1308!-1324 1308[-1419 1270 -1528 1460!-1528 1460|-1621 1470!-1621 1470|-1690 1413!-1690 1413|-1776 1326"/>
                    <Edge fillStyle0="1" edges="!-1776 1326|-1780 1322!-1780 1322[-1876 1206 -1949 1255!-1949 1255[-2022 1303 -2058 1362!-2058 1362|-2072 1397!-2072 1397[-2091 1451 -2066 1521!-2066 1521[-2041 1591 -1943 1654"/>
                    <Edge fillStyle0="1" strokeStyle="1" edges="!-1943 1654|-1934 1660"/>
                    <Edge fillStyle0="1" fillStyle1="2" edges="!-1934 1660|-1980 1596!-1980 1596[-2098 1446 -1968 1371!-1968 1371[-1854 1315 -1736 1430!-1736 1430|-1642 1517!-1642 1517[-1574 1534 -1488 1494!-1488 1494[-1408 1401 -1341 1403!-1341 1403[-1273 1412 -1281 1474"/>
                    <Edge fillStyle1="2" strokeStyle="1" edges="!-1281 1474[-1299 1543 -1329 1615!-1329 1615[-1338 1636 -1367 1647!-1367 1647[-1460 1687 -1587 1754!-1587 1754[-1673 1806 -1725 1777!-1725 1777|-1803 1737!-1803 1737|-1934 1660"/>
                  </edges>
                </DOMShape>
              </elements>
            </DOMFrame>
          </frames>
        </DOMLayer>
        <DOMLayer name="Layer 3" color="#4F4FFF">
          <frames>
            <DOMFrame index="0" motionTweenScale="false" keyMode="8192">
              <elements>
                <DOMShape isFloating="true">
                  <fills>
                    <FillStyle index="1">
                      <SolidColor color="#643E33"/>
                    </FillStyle>
                    <FillStyle index="2">
                      <SolidColor color="#A46C5B"/>
                    </FillStyle>
                  </fills>
                  <strokes>
                    <StrokeStyle index="1">
                      <SolidStroke scaleMode="normal">
                        <fill>
                          <SolidColor/>
                        </fill>
                      </SolidStroke>
                    </StrokeStyle>
                  </strokes>
                  <edges>
                    <Edge fillStyle0="1" strokeStyle="1" edges="!-1231 1491[-1216 1398 -1225 1313!-1225 1313[-1241 1359 -1283 1349!-1283 1349[-1369 1324 -1447 1499!-1447 1499|-1528 1515!-1528 1515|-1593 1471!-1593 1471|-1676 1403"/>
                    <Edge fillStyle0="1" edges="!-1676 1403|-1678 1401!-1678 1401[-1772 1307 -1833 1356!-1833 1356[-1891 1404 -1919 1459!-1919 1459|-1928 1491!-1928 1491[-1939 1540 -1911 1598!-1911 1598[-1884 1657 -1793 1704"/>
                    <Edge fillStyle0="1" strokeStyle="1" edges="!-1793 1704|-1785 1708"/>
                    <Edge fillStyle0="2" strokeStyle="1" edges="!-1785 1708|-1664 1764!-1664 1764|-1593 1792!-1593 1792[-1544 1814 -1473 1760!-1473 1760[-1370 1691 -1291 1649!-1291 1649[-1268 1637 -1261 1618!-1261 1618[-1241 1552 -1231 1491"/>
                    <Edge fillStyle0="2" fillStyle1="1" edges="!-1231 1491[-1228 1435 -1289 1433!-1289 1433[-1347 1437 -1409 1526!-1409 1526[-1482 1568 -1542 1559!-1542 1559|-1631 1490!-1631 1490[-1744 1401 -1840 1459!-1840 1459[-1946 1535 -1831 1657!-1831 1657|-1785 1708"/>
                  </edges>
                </DOMShape>
              </elements>
            </DOMFrame>
          </frames>
        </DOMLayer>
        <DOMLayer name="Layer 4" color="#4F4FFF">
          <frames>
            <DOMFrame index="0" motionTweenScale="false" keyMode="8192">
              <elements>
                <DOMShape isFloating="true">
                  <fills>
                    <FillStyle index="1">
                      <SolidColor color="#643E33"/>
                    </FillStyle>
                    <FillStyle index="2">
                      <SolidColor color="#A46C5B"/>
                    </FillStyle>
                  </fills>
                  <strokes>
                    <StrokeStyle index="1">
                      <SolidStroke scaleMode="normal">
                        <fill>
                          <SolidColor/>
                        </fill>
                      </SolidStroke>
                    </StrokeStyle>
                  </strokes>
                  <edges>
                    <Edge fillStyle0="1" strokeStyle="1" edges="!-1156 1498[-1146 1414 -1157 1337!-1157 1337[-1169 1379 -1207 1372!-1207 1372[-1286 1352 -1351 1512!-1351 1512|-1425 1531!-1425 1531|-1485 1493!-1485 1493|-1562 1433"/>
                    <Edge fillStyle0="1" edges="!-1562 1433|-1565 1430!-1565 1430[-1652 1350 -1706 1396!-1706 1396[-1758 1441 -1780 1491!-1780 1491|-1789 1521!-1789 1521[-1798 1565 -1770 1618!-1770 1618[-1743 1670 -1660 1710"/>
                    <Edge fillStyle0="1" strokeStyle="1" edges="!-1660 1710|-1652 1714"/>
                    <Edge fillStyle0="2" strokeStyle="1" edges="!-1652 1714|-1540 1761!-1540 1761|-1475 1783!-1475 1783[-1429 1802 -1367 1751!-1367 1751[-1275 1685 -1205 1644!-1205 1644[-1184 1632 -1178 1615!-1178 1615[-1163 1554 -1156 1498"/>
                    <Edge fillStyle0="2" fillStyle1="1" edges="!-1156 1498[-1156 1448 -1210 1448!-1210 1448[-1263 1453 -1317 1536!-1317 1536[-1380 1576 -1436 1569!-1436 1569|-1519 1512!-1519 1512[-1625 1433 -1708 1489!-1708 1489[-1803 1562 -1695 1668!-1695 1668|-1652 1714"/>
                  </edges>
                </DOMShape>
              </elements>
            </DOMFrame>
          </frames>
        </DOMLayer>
        <DOMLayer name="Layer 5" color="#4F4FFF">
          <frames>
            <DOMFrame index="0" motionTweenScale="false" keyMode="8192">
              <elements>
                <DOMShape isFloating="true">
                  <fills>
                    <FillStyle index="1">
                      <SolidColor color="#A46C5B"/>
                    </FillStyle>
                    <FillStyle index="2">
                      <SolidColor color="#643E33"/>
                    </FillStyle>
                  </fills>
                  <strokes>
                    <StrokeStyle index="1">
                      <SolidStroke scaleMode="normal">
                        <fill>
                          <SolidColor/>
                        </fill>
                      </SolidStroke>
                    </StrokeStyle>
                  </strokes>
                  <edges>
                    <Edge fillStyle1="1" edges="!-1614 582[-1572 588 -1522 608!-1522 608[-1454 635 -1384 695!-1384 695|-1314 764!-1314 764|-1313 765!-1313 765[-1216 873 -1191 1045"/>
                    <Edge fillStyle0="2" fillStyle1="1" edges="!-1191 1045[-1216 1078 -1264 1112!-1264 1112[-1272 1158 -1309 1232!-1309 1232[-1346 1307 -1406 1382!-1406 1382[-1469 1457 -1558 1601!-1558 1601[-1648 1745 -1729 1712!-1729 1712|-1753 1701!-1753 1701[-1806 1672 -1821 1614!-1821 1614[-1832
 1561 -1812 1509!-1812 1509|-1771 1428!-1771 1428[-1890 1561 -1945 1536!-1945 1536[-1974 1524 -1990 1502!-1990 1502[-2005 1485 -2009 1460!-2009 1460[-2020 1407 -1996 1346!-1996 1346|-1957 1273!-1957 1273[-2069 1397 -2121 1376!-2121 1376
[-2170 1356 -2189 1319!-2189 1319|-2191 1313!-2191 1313[-2204 1281 -2193 1253!-2193 1253|-2186 1240!-2186 1240|-2183 1235!-2183 1235[-1681 612 -1614 582"/>
                    <Edge fillStyle0="2" edges="
!-1614 582|-1665 581!-1665 581[-1709 584 -1719 600"/>
                    <Edge fillStyle0="2" strokeStyle="1" edges="
!-1719 600|-2170 1182!-2170 1182|-2179 1193!-2179 1193[-2224 1248 -2230 1293!-2230 1293|-2230 1297"/>
                    <Edge fillStyle0="2" edges="
!-2230 1297|-2228 1332!-2228 1332|-2223 1345!-2223 1345[-2206 1385 -2173 1402"/>
                    <Edge fillStyle0="2" strokeStyle="1" edges="
!-2173 1402[-2114 1425 -2086 1430!-2086 1430[-2081 1464 -2068 1492"/>
                    <Edge fillStyle0="2" edges="
!-2068 1492|-2058 1528!-2058 1528|-2037 1563!-2037 1563[-2009 1598 -1975 1609"/>
                    <Edge fillStyle0="2" strokeStyle="1" edges="
!-1975 1609|-1929 1616!-1929 1616|-1886 1621!-1886 1621|-1836 1690"/>
                    <Edge fillStyle0="2" edges="
!-1836 1690|-1775 1736!-1775 1736[-1735 1759 -1695 1762"/>
                    <Edge fillStyle0="2" strokeStyle="1" edges="
!-1695 1762[-1579 1764 -1510 1734!-1510 1734[-1457 1707 -1402 1593!-1402 1593|-1383 1551!-1383 1551[-1339 1430 -1278 1367!-1278 1367|-1255 1341!-1255 1341[-1191 1258 -1183 1132"/>
                    <Edge fillStyle0="2" edges="
!-1183 1132[-1184 1087 -1191 1045"/>
                  </edges>
                </DOMShape>
              </elements>
            </DOMFrame>
          </frames>
        </DOMLayer>
      </layers>
    </DOMTimeline>
  </timeline>
</DOMSymbolItem>